[{"id":18692,"name":"ドラえもん","name_cn":"哆啦A梦","air_date":"","weekDayJP":5,"weekDayCN":0,"timeJP":"1800","timeCN":"","image":"http://lain.bgm.tv/pic/cover/g/b4/4f/18692_E04qh.jpg","sites":[],"eps":[{"id":1169607,"type":0,"sort":663,"name":"のびタコ捕獲（ほかく）大作戦！ &amp; カチカチカメラ","name_cn":"大雄章鱼捕获大作战 &amp; 胜利相机","airdate":"2023-02-18","status":"Air"},{"id":1169608,"type":0,"sort":664,"name":"天井うらの宇宙戦争","name_cn":"","airdate":"2023-02-25","status":"NA"},{"id":1174945,"type":1,"sort":664.5,"name":"映画ドラえもん　のび太の宇宙小戦争2021","name_cn":"","airdate":"2023-03-04","status":"NA"},{"type":0,"sort":665,"name":"本周停更","airdate":"2023-03-04"}]},
{"id":81562,"name":"それいけ!アンパンマン","name_cn":"面包超人","air_date":"","weekDayJP":1,"weekDayCN":0,"timeJP":"1600","timeCN":"","image":"http://lain.bgm.tv/pic/cover/g/dd/52/81562_OvgtY.jpg","sites":[],"eps":[{"id":1169631,"type":0,"sort":1607,"name":"","name_cn":"","airdate":"2023-02-17","status":"Air"},{"id":1169632,"type":0,"sort":1608,"name":"","name_cn":"","airdate":"2023-02-24","status":"Today"}]},
{"id":202661,"name":"BORUTO-ボルト- NARUTO NEXT GENERATIONS","name_cn":"火影忍者 博人传之火影次世代","air_date":"","weekDayJP":3,"weekDayCN":7,"timeJP":"1655","timeCN":"1730","image":"http://lain.bgm.tv/pic/cover/g/70/65/202661_Xx5X3.jpg","sites":[{"site":"iqiyi","id":"a_19rrh9f0tx","week":7,"time":"1730","sort":280},{"site":"youku","id":"311801efbfbd111211ef","week":7,"time":"1730","sort":280},{"site":"bilibili","id":"5978","week":7,"time":"1730","sort":841}],"eps":[{"id":1175008,"type":0,"sort":288,"name":"虜","name_cn":"","airdate":"2023-02-19","status":"Air"}]},
{"id":236657,"name":"僕のヒーローアカデミア 第6期","name_cn":"我的英雄学院 第六季","air_date":"","weekDayJP":6,"weekDayCN":0,"timeJP":"1630","timeCN":"","image":"http://lain.bgm.tv/pic/cover/g/99/f4/236657_4MM7M.jpg","sites":[],"eps":[{"id":1130137,"type":0,"sort":133,"name":"刺客","name_cn":"刺客","airdate":"2023-02-18","status":"Air"},{"id":1130138,"type":0,"sort":134,"name":"麗しきレディ・ナガン","name_cn":"美丽的女神纳甘","airdate":"2023-02-25","status":"NA"},{"id":1130139,"type":0,"sort":135,"name":"","name_cn":"","airdate":"2023-03-04","status":"NA"}]},
{"id":270739,"name":"「艦これ」いつかあの海で","name_cn":"舰队Collection 总有一天，在那片海","air_date":"","weekDayJP":4,"weekDayCN":0,"timeJP":"2330","timeCN":"","image":"http://lain.bgm.tv/pic/cover/g/d6/0d/270739_55LdC.jpg","sites":[],"eps":[{"type":0,"sort":8,"name":"本周停更","airdate":"2023-02-19"},{"type":0,"sort":8,"name":"本周停更","airdate":"2023-02-26"},{"type":0,"sort":8,"name":"本周停更","airdate":"2023-03-05"}]},
{"id":296739,"name":"ヴィンランド・サガ SEASON 2","name_cn":"冰海战记 第二季","air_date":"","weekDayJP":1,"weekDayCN":0,"timeJP":"2330","timeCN":"","image":"http://lain.bgm.tv/pic/cover/g/a4/16/296739_71dLe.jpg","sites":[],"eps":[{"id":1174213,"type":1,"sort":6.5,"name":"Drowning in the Shadow","name_cn":"","airdate":"2023-02-14","status":"Air"},{"id":1154641,"type":0,"sort":7,"name":"鉄拳ケティル","name_cn":"铁拳凯特尔","airdate":"2023-02-20","status":"Air"},{"id":1154642,"type":0,"sort":8,"name":"カラッポな男","name_cn":"空虚的人","airdate":"2023-02-27","status":"NA"}]},
{"id":302766,"name":"痛いのは嫌なので防御力に極振りしたいと思います。2","name_cn":"因为太怕痛就全点防御力了。2","air_date":"","weekDayJP":3,"weekDayCN":3,"timeJP":"2230","timeCN":"2330","image":"http://lain.bgm.tv/pic/cover/g/a5/3c/302766_Vqzpu.jpg","sites":[{"site":"bilibili","id":"28412511","week":3,"time":"2330","sort":11}],"eps":[{"id":1153789,"type":0,"sort":6,"name":"防御特化とテイムモンスター。","name_cn":"防御特化与魔宠。","airdate":"2023-02-15","status":"Air"},{"type":0,"sort":7,"name":"本周停更","airdate":"2023-02-22"},{"type":0,"sort":7,"name":"本周停更","airdate":"2023-03-01"}]},
{"id":320839,"name":"虚構推理 Season2","name_cn":"虚构推理 第二季","air_date":"","weekDayJP":1,"weekDayCN":7,"timeJP":"0005","timeCN":"2305","image":"http://lain.bgm.tv/pic/cover/g/44/09/320839_3sL1e.jpg","sites":[{"site":"bilibili","id":"28412512","week":7,"time":"2305","sort":10}],"eps":[{"id":1156448,"type":0,"sort":19,"name":"あるいは星に願いを","name_cn":"或许是寄予星星的愿望","airdate":"2023-02-19","status":"Air"},{"id":1156449,"type":0,"sort":20,"name":"","name_cn":"","airdate":"2023-02-26","status":"NA"},{"id":1156450,"type":0,"sort":21,"name":"","name_cn":"","airdate":"2023-03-05","status":"NA"}]},
{"id":329114,"name":"陰の実力者になりたくて！","name_cn":"想要成为影之实力者！","air_date":"","weekDayJP":3,"weekDayCN":0,"timeJP":"2130","timeCN":"","image":"http://lain.bgm.tv/pic/cover/g/39/96/329114_mB55b.jpg","sites":[],"eps":[{"id":1130662,"type":0,"sort":20,"name":"魔人降臨","name_cn":"魔人降临","airdate":"2023-02-15","status":"Air"},{"id":1175434,"type":1,"sort":20.5,"name":"TVアニメ「陰の実力者になりたくて！」最終話放送記念生配信 〜陰の実力者はカーテンコールをしてみたい！〜","name_cn":"","airdate":"2023-02-22","status":"Air"}]},
{"id":330054,"name":"魔王学院の不適合者 ～史上最強の魔王の始祖、転生して子孫たちの学校へ通う～ Ⅱ","name_cn":"魔王学院的不适任者～史上最强的魔王始祖，转生就读子孙们的学校～ Ⅱ","air_date":"","weekDayJP":6,"weekDayCN":0,"timeJP":"2330","timeCN":"","image":"http://lain.bgm.tv/pic/cover/g/5e/85/330054_86gc8.jpg","sites":[],"eps":[{"type":0,"sort":7,"name":"本周停更","airdate":"2023-02-18"},{"type":0,"sort":7,"name":"本周停更","airdate":"2023-02-25"},{"type":0,"sort":7,"name":"本周停更","airdate":"2023-03-04"}]},
{"id":330334,"name":"The Legend of Heroes 閃の軌跡 Northern War","name_cn":"英雄传说 闪之轨迹：北方战役","air_date":"","weekDayJP":0,"weekDayCN":5,"timeJP":"2230","timeCN":"2100","image":"http://lain.bgm.tv/pic/cover/g/af/3b/330334_w099l.jpg","sites":[],"eps":[{"id":1151564,"type":0,"sort":7,"name":"重ね塗られた鉛色の真実","name_cn":"层层相掩的铅灰真相","airdate":"2023-02-19","status":"Air"},{"id":1151565,"type":0,"sort":8,"name":"決意の間、白茶けた城下","name_cn":"","airdate":"2023-02-26","status":"NA"},{"id":1151566,"type":0,"sort":9,"name":"","name_cn":"","airdate":"2023-03-05","status":"NA"}]},
{"id":331751,"name":"アイドリッシュセブン Third BEAT! 第2クール","name_cn":"IDOLiSH7-偶像星愿- Third BEAT! 第二季","air_date":"","weekDayJP":0,"weekDayCN":0,"timeJP":"2130","timeCN":"","image":"http://lain.bgm.tv/pic/cover/g/ee/63/331751_I6oAT.jpg","sites":[],"eps":[{"id":1154163,"type":0,"sort":29,"name":"掻き混ぜ零れゆく","name_cn":"纷乱后真心显露","airdate":"2023-02-19","status":"Air"},{"id":1154164,"type":0,"sort":30,"name":"","name_cn":"因果早已注定","airdate":"2023-02-26","status":"NA"}]},
{"id":333033,"name":"妖怪ウォッチ♪","name_cn":"妖怪手表♪","air_date":"","weekDayJP":6,"weekDayCN":0,"timeJP":"0000","timeCN":"","image":"http://lain.bgm.tv/pic/cover/g/c9/ea/333033_WW7yB.jpg","sites":[],"eps":[{"id":1173563,"type":0,"sort":92,"name":"妖怪ウォッチ♪特別編　オラとコマじろうのもんげー思い出に残ったお話　大発表スペシャルズラ！","name_cn":"","airdate":"2023-02-17","status":"Air"},{"id":1174729,"type":0,"sort":93,"name":"お家に入りたい／春、まだ来ないの？／妖怪ニャハ体験／４コマさん～ケーキ～／発表！妖怪似顔絵記者会見／ひと狩りいくズラ！～ネガティブーン～","name_cn":"","airdate":"2023-02-24","status":"Today"}]},
{"id":338150,"name":"神達に拾われた男2","name_cn":"被神捡到的男人2","air_date":"","weekDayJP":0,"weekDayCN":0,"timeJP":"2030","timeCN":"","image":"http://lain.bgm.tv/pic/cover/g/7c/2c/338150_mspsF.jpg","sites":[],"eps":[{"id":1156491,"type":0,"sort":7,"name":"リョウマと郷土料理","name_cn":"","airdate":"2023-02-19","status":"Air"},{"id":1156492,"type":0,"sort":8,"name":"","name_cn":"","airdate":"2023-02-26","status":"NA"},{"id":1156493,"type":0,"sort":9,"name":"","name_cn":"","airdate":"2023-03-05","status":"NA"}]},
{"id":340822,"name":"デジモンゴーストゲーム","name_cn":"数码宝贝幽灵游戏","air_date":"","weekDayJP":0,"weekDayCN":0,"timeJP":"0800","timeCN":"","image":"http://lain.bgm.tv/pic/cover/g/52/45/340822_39k9n.jpg","sites":[],"eps":[{"id":1163746,"type":0,"sort":64,"name":"呼ビ声","name_cn":"呼唤声","airdate":"2023-02-19","status":"Air"},{"id":1163747,"type":0,"sort":65,"name":"黒ノ决死圈","name_cn":"黑暗决死圈","airdate":"2023-02-26","status":"NA"},{"type":0,"sort":66,"name":"本周停更","airdate":"2023-03-05"}]},
{"id":341148,"name":"もういっぽん！","name_cn":"再得一胜！","air_date":"","weekDayJP":1,"weekDayCN":0,"timeJP":"0035","timeCN":"","image":"http://lain.bgm.tv/pic/cover/g/e8/53/341148_831I5.jpg","sites":[],"eps":[{"id":1156479,"type":0,"sort":7,"name":"秘密兵器先輩","name_cn":"秘密武器学姐","airdate":"2023-02-19","status":"Air"},{"id":1156480,"type":0,"sort":8,"name":"夢の続き","name_cn":"梦想的延续","airdate":"2023-02-26","status":"NA"},{"id":1156481,"type":0,"sort":9,"name":"","name_cn":"","airdate":"2023-03-05","status":"NA"}]},
{"id":341163,"name":"ブルーロック","name_cn":"蓝色监狱","air_date":"","weekDayJP":0,"weekDayCN":7,"timeJP":"0030","timeCN":"0100","image":"http://lain.bgm.tv/pic/cover/g/b4/db/341163_l525N.jpg","sites":[{"site":"bilibili","id":"28339713","week":7,"time":"0100","sort":17}],"eps":[{"id":1130193,"type":0,"sort":19,"name":"Dancing Boy","name_cn":"","airdate":"2023-02-18","status":"Air"},{"id":1130194,"type":0,"sort":20,"name":"超連動","name_cn":"","airdate":"2023-02-25","status":"NA"},{"id":1130195,"type":0,"sort":21,"name":"","name_cn":"","airdate":"2023-03-04","status":"NA"}]},
{"id":346425,"name":"人間不信の冒険者たちが世界を救うようです","name_cn":"不相信人类的冒险者们好像要去拯救世界","air_date":"","weekDayJP":2,"weekDayCN":0,"timeJP":"2200","timeCN":"","image":"http://lain.bgm.tv/pic/cover/g/be/9a/346425_J8iC6.jpg","sites":[],"eps":[{"id":1156514,"type":0,"sort":6,"name":"算数ベアナックル","name_cn":"算术徒手拳击","airdate":"2023-02-14","status":"Air"},{"id":1156515,"type":0,"sort":7,"name":"賭博指南","name_cn":"赌博指南","airdate":"2023-02-21","status":"Air"},{"id":1156516,"type":0,"sort":8,"name":"麗しのパラディンさま","name_cn":"美丽的圣骑士大人","airdate":"2023-02-28","status":"NA"}]},
{"id":348128,"name":"不滅のあなたへ Season 2","name_cn":"致不灭的你 第二季","air_date":"","weekDayJP":0,"weekDayCN":7,"timeJP":"1800","timeCN":"1900","image":"http://lain.bgm.tv/pic/cover/g/52/88/348128_3fsTT.jpg","sites":[{"site":"bilibili","id":"28339716","week":7,"time":"1900","sort":10}],"eps":[{"id":1094300,"type":0,"sort":17,"name":"守りたいもの","name_cn":"","airdate":"2023-02-19","status":"Air"},{"id":1094301,"type":0,"sort":18,"name":"不死身の死","name_cn":"","airdate":"2023-02-26","status":"NA"},{"id":1094302,"type":0,"sort":19,"name":"","name_cn":"","airdate":"2023-03-05","status":"NA"}]},
{"id":348699,"name":"魔入りました！入間くん 第3シリーズ","name_cn":"入间同学入魔了 第三季","air_date":"","weekDayJP":6,"weekDayCN":0,"timeJP":"1725","timeCN":"","image":"http://lain.bgm.tv/pic/cover/g/99/82/348699_0wWW8.jpg","sites":[],"eps":[{"id":1094322,"type":0,"sort":19,"name":"教師陣の宴","name_cn":"教师们的宴会","airdate":"2023-02-18","status":"Air"},{"id":1094323,"type":0,"sort":20,"name":"悪友／真心クッキング","name_cn":"恶友／真心料理教室","airdate":"2023-02-25","status":"NA"},{"id":1094324,"type":0,"sort":21,"name":"","name_cn":"","airdate":"2023-03-04","status":"NA"}]},
{"id":349389,"name":"カードファイト!! ヴァンガード will+Dress Season2","name_cn":"卡片战斗先导者 will+Dress 第二季","air_date":"","weekDayJP":6,"weekDayCN":0,"timeJP":"0700","timeCN":"","image":"http://lain.bgm.tv/pic/cover/g/1d/b9/349389_AVmDd.jpg","sites":[],"eps":[{"id":1162599,"type":0,"sort":6,"name":"ユニフォーマーズ","name_cn":"","airdate":"2023-02-18","status":"Air"},{"id":1162600,"type":0,"sort":7,"name":"","name_cn":"","airdate":"2023-02-25","status":"NA"},{"id":1162601,"type":0,"sort":8,"name":"","name_cn":"","airdate":"2023-03-04","status":"NA"}]},
{"id":351373,"name":"シュガーアップル・フェアリーテイル","name_cn":"银砂糖师与黑妖精","air_date":"","weekDayJP":5,"weekDayCN":0,"timeJP":"2030","timeCN":"","image":"http://lain.bgm.tv/pic/cover/g/cf/70/351373_15yYP.jpg","sites":[],"eps":[{"id":1156149,"type":0,"sort":7,"name":"いつわりのさよなら","name_cn":"虚假的道别","airdate":"2023-02-17","status":"Air"},{"id":1156150,"type":0,"sort":8,"name":"あなたを見つめつづければ","name_cn":"只要目不转睛地凝视你","airdate":"2023-02-24","status":"Today"},{"id":1156151,"type":0,"sort":9,"name":"","name_cn":"","airdate":"2023-03-03","status":"NA"}]},
{"id":351943,"name":"シャドウバースF","name_cn":"影之诗F","air_date":"","weekDayJP":6,"weekDayCN":0,"timeJP":"0900","timeCN":"","image":"http://lain.bgm.tv/pic/cover/g/d0/c4/351943_HH8IC.jpg","sites":[],"eps":[{"id":1149989,"type":0,"sort":45,"name":"君には期待しているよ","name_cn":"","airdate":"2023-02-18","status":"Air"},{"id":1149990,"type":0,"sort":46,"name":"","name_cn":"","airdate":"2023-02-25","status":"NA"},{"id":1149991,"type":0,"sort":47,"name":"","name_cn":"","airdate":"2023-03-04","status":"NA"}]},
{"id":354042,"name":"イジらないで、長瀞さん 2nd Attack","name_cn":"不要欺负我，长瀞同学 二次攻击","air_date":"","weekDayJP":0,"weekDayCN":0,"timeJP":"0000","timeCN":"","image":"http://lain.bgm.tv/pic/cover/g/71/4c/354042_1CCEt.jpg","sites":[],"eps":[{"id":1156400,"type":0,"sort":7,"name":"センパイの滑りってやっぱそんな感じなんスね","name_cn":"","airdate":"2023-02-18","status":"Air"},{"id":1156401,"type":0,"sort":8,"name":"パイセンさ　ちょーっと体鍛えてみねぇ？","name_cn":"","airdate":"2023-02-25","status":"NA"},{"id":1156402,"type":0,"sort":9,"name":"","name_cn":"","airdate":"2023-03-04","status":"NA"}]},
{"id":355342,"name":"テクノロイド オーバーマインド","name_cn":"超技舞台","air_date":"","weekDayJP":3,"weekDayCN":0,"timeJP":"2300","timeCN":"","image":"http://lain.bgm.tv/pic/cover/g/76/fe/355342_A1KbU.jpg","sites":[],"eps":[{"id":1155531,"type":0,"sort":7,"name":"第7話","name_cn":"第7集","airdate":"2023-02-15","status":"Air"},{"id":1155532,"type":0,"sort":8,"name":"第8話","name_cn":"","airdate":"2023-03-01","status":"NA"},{"type":0,"sort":8,"name":"本周停更","airdate":"2023-02-22"}]},
{"id":355802,"name":"吸血鬼すぐ死ぬ2","name_cn":"吸血鬼马上死2","air_date":"","weekDayJP":1,"weekDayCN":0,"timeJP":"2130","timeCN":"","image":"http://lain.bgm.tv/pic/cover/g/2a/7f/355802_8Dx2f.jpg","sites":[],"eps":[{"id":1151552,"type":0,"sort":7,"name":"Put a sock in it!!! / ちんは国家なり / ジョン 犬ったな","name_cn":"Put a sock in it!!! / 鸡即国家 / 裘恩狗起来","airdate":"2023-02-20","status":"Air"},{"id":1151553,"type":0,"sort":8,"name":"","name_cn":"","airdate":"2023-02-27","status":"NA"}]},
{"id":357210,"name":"もののがたり","name_cn":"物物语","air_date":"","weekDayJP":1,"weekDayCN":2,"timeJP":"2300","timeCN":"0030","image":"http://lain.bgm.tv/pic/cover/g/5a/98/357210_P45ws.jpg","sites":[{"site":"bilibili","id":"28386018","week":2,"time":"0030","sort":8}],"eps":[{"id":1154523,"type":0,"sort":7,"name":"胎動（たいどう）","name_cn":"","airdate":"2023-02-20","status":"Air"},{"id":1154524,"type":0,"sort":8,"name":"","name_cn":"","airdate":"2023-02-27","status":"NA"}]},
{"id":360345,"name":"英雄王、武を極めるため転生す ～そして、世界最強の見習い騎士♀～","name_cn":"英雄王，为了穷尽武道而转生～而后，成为世界最强的见习骑士♀～","air_date":"","weekDayJP":2,"weekDayCN":0,"timeJP":"0045","timeCN":"","image":"http://lain.bgm.tv/pic/cover/g/ec/a2/360345_ooFO2.jpg","sites":[],"eps":[{"id":1156424,"type":0,"sort":7,"name":"天恵武姫の病","name_cn":"天惠武姬的病","airdate":"2023-02-20","status":"Air"},{"id":1156425,"type":0,"sort":8,"name":"","name_cn":"","airdate":"2023-02-27","status":"NA"},{"id":1174042,"type":1,"sort":18,"name":"ミニアニメ ep.18「街を歩けば」","name_cn":"","airdate":"2023-02-14","status":"Air"},{"id":1175378,"type":1,"sort":19,"name":"ミニアニメ ep.19「英雄王式ブートキャンプ」","name_cn":"","airdate":"2023-02-21","status":"Air"}]},
{"id":360611,"name":"ニンジャラ","name_cn":"泡泡糖忍战","air_date":"","weekDayJP":6,"weekDayCN":0,"timeJP":"0930","timeCN":"","image":"http://lain.bgm.tv/pic/cover/g/7e/db/360611_4QJbb.jpg","sites":[],"eps":[{"id":1157442,"type":0,"sort":56,"name":"ギブミー！ニンジャガム！","name_cn":"","airdate":"2023-02-18","status":"Air"},{"id":1157443,"type":0,"sort":57,"name":"アカデミー攻防戦！","name_cn":"","airdate":"2023-02-25","status":"NA"},{"type":0,"sort":58,"name":"本周停更","airdate":"2023-03-04"}]},
{"id":360783,"name":"東京リベンジャーズ 聖夜決戦編","name_cn":"东京复仇者 圣夜决战篇","air_date":"","weekDayJP":0,"weekDayCN":0,"timeJP":"0108","timeCN":"","image":"http://lain.bgm.tv/pic/cover/g/77/de/360783_Psbo0.jpg","sites":[],"eps":[{"id":1156388,"type":0,"sort":31,"name":"Sibling rivalry","name_cn":"","airdate":"2023-02-18","status":"Air"},{"id":1156389,"type":0,"sort":32,"name":"","name_cn":"","airdate":"2023-02-25","status":"NA"},{"id":1156390,"type":0,"sort":33,"name":"","name_cn":"","airdate":"2023-03-04","status":"NA"}]},
{"id":361110,"name":"弱虫ペダル LIMIT BREAK","name_cn":"飙速宅男 突破极限","air_date":"","weekDayJP":6,"weekDayCN":1,"timeJP":"2300","timeCN":"1900","image":"http://lain.bgm.tv/pic/cover/g/4f/ee/361110_73481.jpg","sites":[{"site":"bilibili","id":"28339722","week":1,"time":"1900","sort":22}],"eps":[{"id":1154984,"type":0,"sort":19,"name":"最後のオーダー","name_cn":"","airdate":"2023-02-19","status":"Air"},{"id":1154985,"type":0,"sort":20,"name":"5月の水族館","name_cn":"","airdate":"2023-02-25","status":"NA"},{"type":0,"sort":21,"name":"本周停更","airdate":"2023-03-04"}]},
{"id":361290,"name":"メガトン級ムサシ シーズン2","name_cn":"百万吨级武藏 第二季","air_date":"","weekDayJP":5,"weekDayCN":0,"timeJP":"2100","timeCN":"","image":"http://lain.bgm.tv/pic/cover/g/6f/ce/361290_s1FnH.jpg","sites":[],"eps":[{"id":1157067,"type":0,"sort":26,"name":"閃光","name_cn":"","airdate":"2023-02-17","status":"Air"},{"type":0,"sort":27,"name":"本周停更","airdate":"2023-02-24"},{"type":0,"sort":27,"name":"本周停更","airdate":"2023-03-03"}]},
{"id":362997,"name":"遊☆戯☆王ゴーラッシュ!!","name_cn":"游戏王 Go Rush！！","air_date":"","weekDayJP":0,"weekDayCN":0,"timeJP":"0630","timeCN":"","image":"http://lain.bgm.tv/pic/cover/g/bd/00/362997_8XJ7j.jpg","sites":[],"eps":[{"id":1149850,"type":0,"sort":46,"name":"地球からの侵略者","name_cn":"","airdate":"2023-02-19","status":"Air"},{"id":1149851,"type":0,"sort":47,"name":"ボクちんダマムー！","name_cn":"","airdate":"2023-02-26","status":"NA"},{"type":0,"sort":48,"name":"本周停更","airdate":"2023-03-05"}]},
{"id":363026,"name":"あやかしトライアングル","name_cn":"妖幻三重奏","air_date":"","weekDayJP":2,"weekDayCN":0,"timeJP":"0000","timeCN":"","image":"http://lain.bgm.tv/pic/cover/g/f6/2b/363026_191za.jpg","sites":[],"eps":[{"type":0,"sort":5,"name":"本周停更","airdate":"2023-02-13"},{"type":0,"sort":5,"name":"本周停更","airdate":"2023-02-20"},{"type":0,"sort":5,"name":"本周停更","airdate":"2023-02-27"},{"type":0,"sort":5,"name":"本周停更","airdate":"2023-03-06"}]},
{"id":363308,"name":"ツンデレ悪役令嬢リーゼロッテと実況の遠藤くんと解説の小林さん","name_cn":"傲娇恶役大小姐莉泽洛特与实况转播远藤君和解说员小林","air_date":"","weekDayJP":6,"weekDayCN":6,"timeJP":"0125","timeCN":"0155","image":"http://lain.bgm.tv/pic/cover/g/db/31/363308_461Oh.jpg","sites":[{"site":"bilibili","id":"28386016","week":6,"time":"0155","sort":9}],"eps":[{"id":1156137,"type":0,"sort":7,"name":"神託とショタと生放送","name_cn":"神谕和少年和现场直播","airdate":"2023-02-17","status":"Air"},{"id":1156138,"type":0,"sort":8,"name":"師弟と仮面とツンギレ令嬢","name_cn":"师徒和面具和激怒大小姐","airdate":"2023-02-24","status":"Today"},{"id":1156139,"type":0,"sort":9,"name":"","name_cn":"","airdate":"2023-03-03","status":"NA"}]},
{"id":364468,"name":"うる星やつら","name_cn":"福星小子","air_date":"","weekDayJP":5,"weekDayCN":0,"timeJP":"0045","timeCN":"","image":"http://lain.bgm.tv/pic/cover/g/c1/e8/364468_8AI0E.jpg","sites":[],"eps":[{"id":1114906,"type":0,"sort":18,"name":"き・え・な・いルージュマジック!!／必殺！ヤミナベ","name_cn":"擦不掉的魔法口红！！／必杀！黑暗火锅","airdate":"2023-02-16","status":"Air"},{"id":1114907,"type":0,"sort":19,"name":"魔境！戦慄の密林 ／ 酔っぱらいブギ","name_cn":"魔境！战栗的密林／喝醉洒的BOOGIE","airdate":"2023-02-23","status":"Air"},{"id":1114908,"type":0,"sort":20,"name":"","name_cn":"","airdate":"2023-03-02","status":"NA"}]},
{"id":364822,"name":"お隣の天使様にいつの間にか駄目人間にされていた件","name_cn":"关于邻家的天使大人不知不觉把我惯成了废人这档子事","air_date":"","weekDayJP":6,"weekDayCN":0,"timeJP":"2130","timeCN":"","image":"http://lain.bgm.tv/pic/cover/g/37/d1/364822_JGG68.jpg","sites":[],"eps":[{"id":1156347,"type":0,"sort":7,"name":"天使様との約束","name_cn":"与天使的约定","airdate":"2023-02-18","status":"Air"},{"id":1156348,"type":0,"sort":8,"name":"","name_cn":"","airdate":"2023-02-25","status":"NA"},{"id":1156349,"type":0,"sort":9,"name":"","name_cn":"","airdate":"2023-03-04","status":"NA"}]},
{"id":366165,"name":"便利屋斎藤さん、異世界に行く","name_cn":"万事屋斋藤、到异世界","air_date":"","weekDayJP":0,"weekDayCN":0,"timeJP":"2130","timeCN":"","image":"http://lain.bgm.tv/pic/cover/g/5a/a2/366165_Ds2pa.jpg","sites":[],"eps":[{"id":1154838,"type":0,"sort":7,"name":"極限の接触","name_cn":"极限接触","airdate":"2023-02-19","status":"Air"},{"id":1154839,"type":0,"sort":8,"name":"戦いで得たもの","name_cn":"","airdate":"2023-02-26","status":"NA"},{"id":1154840,"type":0,"sort":9,"name":"","name_cn":"","airdate":"2023-03-05","status":"NA"}]},
{"id":366250,"name":"大雪海のカイナ","name_cn":"大雪海的卡纳","air_date":"","weekDayJP":4,"weekDayCN":4,"timeJP":"0005","timeCN":"0125","image":"http://lain.bgm.tv/pic/cover/g/de/2a/366250_4d4tj.jpg","sites":[{"site":"bilibili","id":"28386015","week":4,"time":"0125","sort":9}],"eps":[{"id":1156502,"type":0,"sort":6,"name":"籠の中のリリハ","name_cn":"笼中的莉莉哈","airdate":"2023-02-15","status":"Air"},{"id":1156503,"type":0,"sort":7,"name":"要塞の国","name_cn":"要塞之国","airdate":"2023-02-22","status":"Air"},{"id":1156504,"type":0,"sort":8,"name":"","name_cn":"","airdate":"2023-03-01","status":"NA"}]},
{"id":366507,"name":"最強陰陽師の異世界転生記","name_cn":"最强阴阳师的异世界转生记","air_date":"","weekDayJP":6,"weekDayCN":0,"timeJP":"2230","timeCN":"","image":"http://lain.bgm.tv/pic/cover/g/35/da/366507_M8q13.jpg","sites":[],"eps":[{"id":1156364,"type":0,"sort":7,"name":"兄妹","name_cn":"","airdate":"2023-02-18","status":"Air"},{"id":1156365,"type":0,"sort":8,"name":"","name_cn":"","airdate":"2023-02-25","status":"NA"},{"id":1156366,"type":0,"sort":9,"name":"","name_cn":"","airdate":"2023-03-04","status":"NA"}]},
{"id":368116,"name":"NieR: Automata Ver1.1a","name_cn":"尼尔：自动人形 Ver1.1a","air_date":"","weekDayJP":6,"weekDayCN":0,"timeJP":"2300","timeCN":"","image":"http://lain.bgm.tv/pic/cover/g/da/43/368116_T5lPp.jpg","sites":[],"eps":[{"id":1157532,"type":0,"sort":4,"name":"a mountain too [H]igh","name_cn":"","airdate":"2023-02-18","status":"Air"},{"type":0,"sort":5,"name":"本周停更","airdate":"2023-02-25"},{"type":0,"sort":5,"name":"本周停更","airdate":"2023-03-04"}]},
{"id":372925,"name":"キャップ革命 ボトルマンDX","name_cn":"帽子革命瓶子人 DX","air_date":"","weekDayJP":0,"weekDayCN":0,"timeJP":"0830","timeCN":"","image":"http://lain.bgm.tv/pic/cover/g/9d/ee/372925_b0q8j.jpg","sites":[],"eps":[{"id":1174244,"type":0,"sort":46,"name":"さよなら帆狩リョウ","name_cn":"","airdate":"2023-02-19","status":"Air"},{"id":1175418,"type":0,"sort":47,"name":"帰ってきた流行ポンタ","name_cn":"","airdate":"2023-02-26","status":"NA"}]},
{"id":373390,"name":"HIGH CARD","name_cn":"至高之牌","air_date":"","weekDayJP":1,"weekDayCN":0,"timeJP":"1900","timeCN":"","image":"http://lain.bgm.tv/pic/cover/g/ec/a0/373390_qMa5c.jpg","sites":[],"eps":[{"id":1156412,"type":0,"sort":7,"name":"LOVE &amp; FAKE","name_cn":"爱与虚假","airdate":"2023-02-20","status":"Air"},{"id":1156413,"type":0,"sort":8,"name":"HEAT UP","name_cn":"烧热","airdate":"2023-02-27","status":"NA"}]},
{"id":374206,"name":"スパイ教室","name_cn":"间谍教室","air_date":"","weekDayJP":4,"weekDayCN":0,"timeJP":"2130","timeCN":"","image":"http://lain.bgm.tv/pic/cover/g/f8/36/374206_faPhx.jpg","sites":[],"eps":[{"id":1156114,"type":0,"sort":7,"name":"File 《草原》のサラ","name_cn":"档案 《草原》莎拉","airdate":"2023-02-16","status":"Air"},{"id":1156115,"type":0,"sort":8,"name":"","name_cn":"","airdate":"2023-03-02","status":"NA"},{"type":0,"sort":8,"name":"本周停更","airdate":"2023-02-23"}]},
{"id":374319,"name":"犬になったら好きな人に拾われた。","name_cn":"生而为狗，我很幸福","air_date":"","weekDayJP":4,"weekDayCN":0,"timeJP":"2000","timeCN":"","image":"http://lain.bgm.tv/pic/cover/g/83/d3/374319_JSG4d.jpg","sites":[],"eps":[{"id":1156161,"type":0,"sort":7,"name":"ハウス対決。","name_cn":"狗屋对决。","airdate":"2023-02-17","status":"Air"},{"id":1156162,"type":0,"sort":8,"name":"学園潜入。","name_cn":"","airdate":"2023-02-24","status":"Today"},{"id":1156163,"type":0,"sort":9,"name":"","name_cn":"","airdate":"2023-03-03","status":"NA"}]},
{"id":374563,"name":"永久少年 Eternal Boys","name_cn":"永久少年 Eternal Boys","air_date":"","weekDayJP":2,"weekDayCN":0,"timeJP":"0120","timeCN":"","image":"http://lain.bgm.tv/pic/cover/g/b1/d4/374563_0SM4I.jpg","sites":[],"eps":[{"id":1123464,"type":0,"sort":19,"name":"CM","name_cn":"","airdate":"2023-02-20","status":"Air"},{"id":1123465,"type":0,"sort":20,"name":"経営不振","name_cn":"","airdate":"2023-02-27","status":"NA"}]},
{"id":376137,"name":"異世界のんびり農家","name_cn":"异世界悠闲农家","air_date":"","weekDayJP":5,"weekDayCN":0,"timeJP":"2000","timeCN":"","image":"http://lain.bgm.tv/pic/cover/g/09/1a/376137_OjCOB.jpg","sites":[],"eps":[{"id":1156173,"type":0,"sort":7,"name":"おもてなしの心","name_cn":"款待之心","airdate":"2023-02-17","status":"Air"},{"id":1156174,"type":0,"sort":8,"name":"研究者と二人のお嬢さま","name_cn":"研究家与两位大小姐","airdate":"2023-02-24","status":"Today"},{"id":1156175,"type":0,"sort":9,"name":"","name_cn":"","airdate":"2023-03-03","status":"NA"}]},
{"id":376399,"name":"真・進化の実～知らないうちに勝ち組人生～","name_cn":"真・进化果实～不知不觉踏上胜利的人生～","air_date":"","weekDayJP":6,"weekDayCN":6,"timeJP":"0023","timeCN":"0023","image":"http://lain.bgm.tv/pic/cover/g/4f/23/376399_E2X0e.jpg","sites":[{"site":"bilibili","id":"28340325","week":6,"time":"0023","sort":27}],"eps":[{"id":1158116,"type":0,"sort":6,"name":"決戦！バーバドル魔法学園","name_cn":"决战！巴巴多尔魔法学园","airdate":"2023-02-17","status":"Air"},{"id":1158117,"type":0,"sort":7,"name":"","name_cn":"诚一，死亡","airdate":"2023-02-24","status":"Today"},{"id":1158118,"type":0,"sort":8,"name":"","name_cn":"","airdate":"2023-03-03","status":"NA"}]},
{"id":377556,"name":"D4DJ All Mix","name_cn":"","air_date":"","weekDayJP":5,"weekDayCN":0,"timeJP":"2200","timeCN":"","image":"http://lain.bgm.tv/pic/cover/g/2f/7e/377556_e133E.jpg","sites":[],"eps":[{"id":1160109,"type":0,"sort":6,"name":"Jun.「ハクチュウム」","name_cn":"","airdate":"2023-02-17","status":"Air"},{"id":1160110,"type":0,"sort":7,"name":"Jul.「ミンナカワイイ！」","name_cn":"","airdate":"2023-02-24","status":"Today"},{"id":1160111,"type":0,"sort":8,"name":"","name_cn":"","airdate":"2023-03-03","status":"NA"}]},
{"id":378860,"name":"クールドジ男子","name_cn":"呆萌酷男孩","air_date":"","weekDayJP":2,"weekDayCN":2,"timeJP":"0030","timeCN":"0130","image":"http://lain.bgm.tv/pic/cover/g/9d/de/378860_q0N79.jpg","sites":[{"site":"bilibili","id":"28339724","week":2,"time":"0130","sort":20}],"eps":[{"id":1154652,"type":0,"sort":19,"name":"メンバー入り","name_cn":"新成员加入","airdate":"2023-02-20","status":"Air"},{"id":1154653,"type":0,"sort":20,"name":"苦手なもの","name_cn":"不擅长的事物","airdate":"2023-02-27","status":"NA"},{"type":0,"sort":21,"name":"本周停更","airdate":"2023-03-06"}]},
{"id":378862,"name":"お兄ちゃんはおしまい！","name_cn":"别当欧尼酱了！","air_date":"","weekDayJP":4,"weekDayCN":0,"timeJP":"2230","timeCN":"","image":"http://lain.bgm.tv/pic/cover/g/7e/ca/378862_PSRrl.jpg","sites":[],"eps":[{"id":1156102,"type":0,"sort":7,"name":"まひろとロールプレイ","name_cn":"真寻与角色扮演","airdate":"2023-02-16","status":"Air"},{"id":1156103,"type":0,"sort":8,"name":"まひろとはじめての女子会","name_cn":"真寻与初次女孩聚会","airdate":"2023-02-23","status":"Air"},{"id":1156104,"type":0,"sort":9,"name":"","name_cn":"","airdate":"2023-03-02","status":"NA"}]},
{"id":379687,"name":"冰剣の魔術師が世界を統べる","name_cn":"冰剑的魔术师将要统一世界","air_date":"","weekDayJP":5,"weekDayCN":0,"timeJP":"0058","timeCN":"","image":"http://lain.bgm.tv/pic/cover/g/f8/95/379687_51Jj6.jpg","sites":[],"eps":[{"id":1156090,"type":0,"sort":7,"name":"世界最強の魔術師である少女は、魔術学院に潜入する","name_cn":"世界最强的魔术师少女，潜入魔法学院","airdate":"2023-02-16","status":"Air"},{"id":1156091,"type":0,"sort":8,"name":"世界最強の魔術師である少年は、薔薇を鼓舞する","name_cn":"世界最强的魔术师少年，鼓舞玫瑰","airdate":"2023-02-23","status":"Air"},{"id":1156092,"type":0,"sort":9,"name":"","name_cn":"","airdate":"2023-03-02","status":"NA"}]},
{"id":381793,"name":"久保さんは僕を許さない","name_cn":"久保同学不放过我","air_date":"","weekDayJP":2,"weekDayCN":2,"timeJP":"2030","timeCN":"2330","image":"http://lain.bgm.tv/pic/cover/g/12/39/381793_oNshs.jpg","sites":[{"site":"bilibili","id":"28340407","week":2,"time":"2330","sort":20}],"eps":[{"id":1156538,"type":0,"sort":6,"name":"保健室と主人公","name_cn":"保健室和主人公","airdate":"2023-02-14","status":"Air"},{"type":0,"sort":7,"name":"本周停更","airdate":"2023-02-21"},{"type":0,"sort":7,"name":"本周停更","airdate":"2023-02-28"}]},
{"id":385411,"name":"僕とロボコ","name_cn":"我与机器子","air_date":"","weekDayJP":0,"weekDayCN":0,"timeJP":"2340","timeCN":"","image":"http://lain.bgm.tv/pic/cover/g/64/3c/385411_1Jiqi.jpg","sites":[],"eps":[{"id":1169538,"type":0,"sort":11,"name":"雪とロボコ","name_cn":"雪与机器子","airdate":"2023-02-19","status":"Air"},{"id":1169539,"type":0,"sort":12,"name":"","name_cn":"","airdate":"2023-02-26","status":"NA"}]},
{"id":388170,"name":"TRIGUN STAMPEDE","name_cn":"枪神 斯坦比特","air_date":"","weekDayJP":6,"weekDayCN":0,"timeJP":"2215","timeCN":"","image":"http://lain.bgm.tv/pic/cover/g/47/98/388170_3O3ht.jpg","sites":[],"eps":[{"id":1156335,"type":0,"sort":7,"name":"WOLFWOOD","name_cn":"伍夫伍德","airdate":"2023-02-18","status":"Air"},{"id":1156336,"type":0,"sort":8,"name":"Our Home.","name_cn":"","airdate":"2023-02-25","status":"NA"},{"id":1156337,"type":0,"sort":9,"name":"","name_cn":"","airdate":"2023-03-04","status":"NA"}]},
{"id":388993,"name":"氷属性男子とクールな同僚女子","name_cn":"冰属性男子与酷酷女同事","air_date":"","weekDayJP":2,"weekDayCN":2,"timeJP":"2130","timeCN":"2230","image":"http://lain.bgm.tv/pic/cover/g/8a/27/388993_gdLGU.jpg","sites":[{"site":"bilibili","id":"28385999","week":2,"time":"2230","sort":9}],"eps":[{"id":1144753,"type":0,"sort":7,"name":"ドキッと！ハロウィンコスプレ大会","name_cn":"心跳！万圣夜扮装大赛","airdate":"2023-02-15","status":"Air"},{"id":1144754,"type":0,"sort":8,"name":"妹登場！スキー場のクリスマス","name_cn":"妹妹登场！滑雪场的圣诞节","airdate":"2023-02-22","status":"Air"},{"id":1144755,"type":0,"sort":9,"name":"","name_cn":"","airdate":"2023-03-01","status":"NA"}]},
{"id":390239,"name":"ノケモノたちの夜","name_cn":"沦落者之夜","air_date":"","weekDayJP":0,"weekDayCN":0,"timeJP":"2100","timeCN":"","image":"http://lain.bgm.tv/pic/cover/g/3c/fd/390239_baBMz.jpg","sites":[],"eps":[{"id":1156436,"type":0,"sort":7,"name":"開幕は過去の銃声と共に","name_cn":"","airdate":"2023-02-19","status":"Air"},{"id":1156437,"type":0,"sort":8,"name":"","name_cn":"","airdate":"2023-02-26","status":"NA"},{"id":1156438,"type":0,"sort":9,"name":"","name_cn":"","airdate":"2023-03-05","status":"NA"}]},
{"id":390618,"name":"トモちゃんは女の子!","name_cn":"智酱是女生！","air_date":"","weekDayJP":3,"weekDayCN":0,"timeJP":"2330","timeCN":"","image":"http://lain.bgm.tv/pic/cover/g/a9/40/390618_964CX.jpg","sites":[],"eps":[{"id":1149269,"type":0,"sort":7,"name":"淳一郎の誓い／トモが水着に着替えたら","name_cn":"淳一郎的誓言／如果小智换了泳装","airdate":"2023-02-15","status":"Air"},{"id":1149270,"type":0,"sort":8,"name":"夏祭りの夜／二人の距離感","name_cn":"夏日庆典的夜晚／两人的距离感","airdate":"2023-02-22","status":"Air"},{"id":1149271,"type":0,"sort":9,"name":"","name_cn":"","airdate":"2023-03-01","status":"NA"}]},
{"id":392349,"name":"解雇された暗黒兵士（30代）のスローなセカンドライフ","name_cn":"被解雇的暗黑士兵（30岁）慢生活的第二人生","air_date":"","weekDayJP":6,"weekDayCN":6,"timeJP":"2100","timeCN":"2100","image":"http://lain.bgm.tv/pic/cover/g/df/e2/392349_GVEl4.jpg","sites":[{"site":"bilibili","id":"28344587","week":6,"time":"2100","sort":30}],"eps":[{"id":1156323,"type":0,"sort":7,"name":"ダリエル、あの技を使う。","name_cn":"达利艾尔，使出那一招。","airdate":"2023-02-18","status":"Air"},{"id":1156324,"type":0,"sort":8,"name":"ダリエル、奔走する。","name_cn":"达利艾尔，四处奔走。","airdate":"2023-02-25","status":"NA"},{"id":1156325,"type":0,"sort":9,"name":"","name_cn":"","airdate":"2023-03-04","status":"NA"}]},
{"id":393217,"name":"老後に備えて異世界で8万枚の金貨を貯めます","name_cn":"为了养老金去异界存八万金","air_date":"","weekDayJP":0,"weekDayCN":0,"timeJP":"0100","timeCN":"","image":"http://lain.bgm.tv/pic/cover/g/76/d1/393217_yhCbh.jpg","sites":[],"eps":[{"id":1156311,"type":0,"sort":7,"name":"ミツハの大冒険","name_cn":"光波的大冒险","airdate":"2023-02-18","status":"Air"},{"id":1156312,"type":0,"sort":8,"name":"","name_cn":"","airdate":"2023-02-25","status":"NA"},{"id":1156313,"type":0,"sort":9,"name":"","name_cn":"","airdate":"2023-03-04","status":"NA"}]},
{"id":393238,"name":"とんでもスキルで異世界放浪メシ","name_cn":"拥有超常技能的异世界流浪美食家","air_date":"","weekDayJP":2,"weekDayCN":0,"timeJP":"2300","timeCN":"","image":"http://lain.bgm.tv/pic/cover/g/3f/cf/393238_ZB8x3.jpg","sites":[],"eps":[{"id":1156526,"type":0,"sort":6,"name":"成長は突然やってくる","name_cn":"成长会突然降临","airdate":"2023-02-14","status":"Air"},{"id":1156527,"type":0,"sort":7,"name":"狼は魔獣と踊る","name_cn":"狼与魔兽共舞","airdate":"2023-02-21","status":"Air"},{"id":1156528,"type":0,"sort":8,"name":"ボスキャラはどれも美味い","name_cn":"头目全都很好吃","airdate":"2023-02-28","status":"NA"}]},
{"id":395714,"name":"転生王女と天才令嬢の魔法革命","name_cn":"转生公主与天才千金的魔法革命","air_date":"","weekDayJP":3,"weekDayCN":0,"timeJP":"2000","timeCN":"","image":"http://lain.bgm.tv/pic/cover/g/fd/3c/395714_5EeZx.jpg","sites":[],"eps":[{"id":1155488,"type":0,"sort":7,"name":"開祖と助手の魔学講演","name_cn":"创始人与助手的魔学演讲","airdate":"2023-02-15","status":"Air"},{"id":1155489,"type":0,"sort":8,"name":"怪物と凡愚の魔法定義","name_cn":"怪物与庸才的魔法定义","airdate":"2023-02-22","status":"Air"},{"id":1155490,"type":0,"sort":9,"name":"姉弟と誰がための王冠","name_cn":"姐弟与为谁存在的王冠","airdate":"2023-03-01","status":"NA"}]},
{"id":395782,"name":"ジョジョの奇妙な冒険 ストーンオーシャン 第3クール","name_cn":"JOJO的奇妙冒险 石之海 Part.3","air_date":"","weekDayJP":5,"weekDayCN":0,"timeJP":"2330","timeCN":"","image":"http://lain.bgm.tv/pic/cover/g/f7/40/395782_2KxQx.jpg","sites":[],"eps":[{"id":1122374,"type":0,"sort":31,"name":"ヘビー・ウェザー　その②","name_cn":"狂风骤雨 其二","airdate":"2023-02-17","status":"Air"},{"id":1122375,"type":0,"sort":32,"name":"ヘビー・ウェザー　その③","name_cn":"狂风骤雨 其三","airdate":"2023-02-24","status":"Today"},{"id":1122376,"type":0,"sort":33,"name":"新月の重力","name_cn":"新月的重力","airdate":"2023-03-03","status":"NA"}]},
{"id":396443,"name":"デュエル・マスターズWIN","name_cn":"决斗大师WIN","air_date":"","weekDayJP":0,"weekDayCN":0,"timeJP":"0730","timeCN":"","image":"http://lain.bgm.tv/pic/cover/g/17/73/396443_l164w.jpg","sites":[],"eps":[{"id":1147767,"type":0,"sort":24,"name":"崩壊 ！！ふたつの世界","name_cn":"","airdate":"2023-02-19","status":"Air"},{"id":1174239,"type":0,"sort":25,"name":"大逆転！！決着の行方","name_cn":"","airdate":"2023-02-26","status":"NA"},{"id":1174240,"type":0,"sort":26,"name":"","name_cn":"","airdate":"2023-03-05","status":"NA"}]},
{"id":396487,"name":"チキップダンサーズ 2期","name_cn":"小鸡舞者 第二季","air_date":"","weekDayJP":2,"weekDayCN":0,"timeJP":"0745","timeCN":"","image":"http://lain.bgm.tv/pic/cover/g/06/b0/396487_rCOEj.jpg","sites":[],"eps":[{"id":1154127,"type":0,"sort":20,"name":"UFOこいこい","name_cn":"","airdate":"2023-02-14","status":"Air"},{"id":1154128,"type":0,"sort":21,"name":"うみであちあち","name_cn":"","airdate":"2023-02-21","status":"Air"},{"id":1154129,"type":0,"sort":22,"name":"どうぶつアニマル","name_cn":"","airdate":"2023-02-28","status":"NA"}]},
{"id":396988,"name":"ツルネ －つながりの一射－","name_cn":"弦音 -联系的一箭-","air_date":"","weekDayJP":3,"weekDayCN":0,"timeJP":"2300","timeCN":"","image":"http://lain.bgm.tv/pic/cover/g/01/f2/396988_9dQZ2.jpg","sites":[],"eps":[{"id":1155499,"type":0,"sort":7,"name":"的射る心","name_cn":"瞄准之心","airdate":"2023-02-15","status":"Air"},{"id":1155500,"type":0,"sort":8,"name":"矢筋道","name_cn":"箭矢飞行方向","airdate":"2023-02-22","status":"Air"},{"id":1155501,"type":0,"sort":9,"name":"","name_cn":"","airdate":"2023-03-01","status":"NA"}]},
{"id":398762,"name":"ぷにるんず","name_cn":"噗尼轮轮","air_date":"","weekDayJP":0,"weekDayCN":0,"timeJP":"0845","timeCN":"","image":"http://lain.bgm.tv/pic/cover/g/e1/9b/398762_NGTSG.jpg","sites":[],"eps":[{"id":1172944,"type":0,"sort":20,"name":"パパ、あいるんをおせわするん♪","name_cn":"","airdate":"2023-02-19","status":"Air"},{"id":1172945,"type":0,"sort":21,"name":"ぷにるんず、みんなでお掃除するん♪","name_cn":"","airdate":"2023-02-26","status":"NA"},{"id":1172946,"type":0,"sort":22,"name":"","name_cn":"","airdate":"2023-03-05","status":"NA"}]},
{"id":401786,"name":"魔術士オーフェンはぐれ旅 アーバンラマ編","name_cn":"魔术士奥芬的无赖之旅 拉玛城篇","air_date":"","weekDayJP":3,"weekDayCN":0,"timeJP":"1930","timeCN":"","image":"http://lain.bgm.tv/pic/cover/g/29/67/401786_3CQ31.jpg","sites":[],"eps":[{"id":1163756,"type":0,"sort":5,"name":"蟲の紋章の剣","name_cn":"虫之纹章之剑","airdate":"2023-02-15","status":"Air"},{"id":1163757,"type":0,"sort":6,"name":"我が心求めよ悪魔","name_cn":"恶魔啊 渴求吾之心灵","airdate":"2023-02-22","status":"Air"},{"id":1163758,"type":0,"sort":7,"name":"","name_cn":"月光啊 照亮吾之奇袭","airdate":"2023-03-01","status":"NA"}]},
{"id":401960,"name":"にじよん あにめーしょん","name_cn":"虹四动画","air_date":"","weekDayJP":5,"weekDayCN":0,"timeJP":"2054","timeCN":"","image":"http://lain.bgm.tv/pic/cover/g/31/aa/401960_nQcWc.jpg","sites":[],"eps":[{"id":1156185,"type":0,"sort":7,"name":"ランジュとジョーカー","name_cn":"岚珠与joker","airdate":"2023-02-17","status":"Air"},{"id":1156186,"type":0,"sort":8,"name":"","name_cn":"","airdate":"2023-02-24","status":"Today"},{"id":1156187,"type":0,"sort":9,"name":"","name_cn":"","airdate":"2023-03-03","status":"NA"}]},
{"id":402223,"name":"ダンジョンに出会いを求めるのは間違っているだろうか Ⅳ 深章 厄災編","name_cn":"期待在地下城邂逅有错吗 Ⅳ 深章 灾厄篇","air_date":"","weekDayJP":4,"weekDayCN":0,"timeJP":"2200","timeCN":"","image":"http://lain.bgm.tv/pic/cover/g/9e/4b/402223_xN4rh.jpg","sites":[],"eps":[{"id":1129765,"type":0,"sort":18,"name":"迷宮決死行（デスパレート）","name_cn":"迷宫决死行（Desperate）","airdate":"2023-02-17","status":"Air"},{"id":1129766,"type":0,"sort":19,"name":"闘技場（コロシアム）","name_cn":"竞技场（Koroshiamu）","airdate":"2023-02-24","status":"Today"},{"id":1129767,"type":0,"sort":20,"name":"","name_cn":"","airdate":"2023-03-03","status":"NA"}]},
{"id":402659,"name":"UniteUp!","name_cn":"众星齐聚","air_date":"","weekDayJP":6,"weekDayCN":0,"timeJP":"2230","timeCN":"","image":"http://lain.bgm.tv/pic/cover/g/03/6b/402659_r50j7.jpg","sites":[],"eps":[{"id":1156297,"type":0,"sort":5,"name":"立ち上がらないと","name_cn":"","airdate":"2023-02-18","status":"Air"},{"id":1156298,"type":0,"sort":6,"name":"","name_cn":"","airdate":"2023-02-25","status":"NA"},{"id":1156299,"type":0,"sort":7,"name":"","name_cn":"","airdate":"2023-03-04","status":"NA"}]},
{"id":403020,"name":"アルスの巨獣","name_cn":"阿鲁斯的巨兽","air_date":"","weekDayJP":6,"weekDayCN":6,"timeJP":"0055","timeCN":"0100","image":"http://lain.bgm.tv/pic/cover/g/86/f8/403020_IDDVV.jpg","sites":[{"site":"bilibili","id":"28339956","week":6,"time":"0100","sort":9}],"eps":[{"id":1153730,"type":0,"sort":7,"name":"ムラサキは角の記憶","name_cn":"紫色是犄角的记忆","airdate":"2023-02-17","status":"Air"},{"id":1153731,"type":0,"sort":8,"name":"同一性の証明","name_cn":"同一性的证明","airdate":"2023-02-24","status":"Today"},{"id":1153732,"type":0,"sort":9,"name":"","name_cn":"","airdate":"2023-03-03","status":"NA"}]},
{"id":403379,"name":"REVENGER","name_cn":"复仇者","air_date":"","weekDayJP":4,"weekDayCN":0,"timeJP":"2000","timeCN":"","image":"http://lain.bgm.tv/pic/cover/g/54/13/403379_D2ICB.jpg","sites":[],"eps":[{"id":1156078,"type":0,"sort":7,"name":"Rosy Pitfall","name_cn":"玫瑰色的陷阱","airdate":"2023-02-16","status":"Air"},{"id":1156079,"type":0,"sort":8,"name":"Two of a Trade Never Agree","name_cn":"同行是冤家","airdate":"2023-02-23","status":"Air"},{"id":1156080,"type":0,"sort":9,"name":"","name_cn":"","airdate":"2023-03-02","status":"NA"}]},
{"id":403671,"name":"KJファイル 第2期","name_cn":"怪兽档案 第二季","air_date":"","weekDayJP":1,"weekDayCN":0,"timeJP":"0135","timeCN":"","image":"http://lain.bgm.tv/pic/cover/g/0e/a4/403671_d6GGL.jpg","sites":[],"eps":[{"id":1156467,"type":0,"sort":20,"name":"マグニグマ／ガララボラス","name_cn":"","airdate":"2023-02-19","status":"Air"},{"id":1156468,"type":0,"sort":21,"name":"","name_cn":"","airdate":"2023-02-26","status":"NA"},{"id":1156469,"type":0,"sort":22,"name":"","name_cn":"","airdate":"2023-03-05","status":"NA"}]},
{"id":405659,"name":"Buddy Daddies","name_cn":"杀手奶爸","air_date":"","weekDayJP":5,"weekDayCN":0,"timeJP":"2300","timeCN":"","image":"http://lain.bgm.tv/pic/cover/g/39/70/405659_1ReXS.jpg","sites":[],"eps":[{"id":1156126,"type":0,"sort":7,"name":"AFTER RAIN COMES FAIR WEATHER","name_cn":"雨过天晴","airdate":"2023-02-17","status":"Air"},{"id":1156127,"type":0,"sort":8,"name":"","name_cn":"","airdate":"2023-02-24","status":"Today"},{"id":1156128,"type":0,"sort":9,"name":"","name_cn":"","airdate":"2023-03-03","status":"NA"}]},
{"id":411246,"name":"ポケットモンスター めざせポケモンマスター","name_cn":"宝可梦 旅途 目标是宝可梦大师","air_date":"","weekDayJP":5,"weekDayCN":0,"timeJP":"1755","timeCN":"","image":"http://lain.bgm.tv/pic/cover/g/f8/02/411246_zeffD.jpg","sites":[],"eps":[{"id":1153911,"type":0,"sort":6,"name":"そして、おなじ月をみている！","name_cn":"","airdate":"2023-02-17","status":"Air"},{"id":1153912,"type":0,"sort":7,"name":"ラプラスにのって♪","name_cn":"","airdate":"2023-02-24","status":"Today"},{"id":1153913,"type":0,"sort":8,"name":"","name_cn":"","airdate":"2023-03-03","status":"NA"}]}]
