[{"t":"pixiv","n":11464,"i":84},{"t":"～技术宅真可怕～","n":9068,"i":11},{"t":"靠谱人生茶话会","n":8513,"i":364},{"t":"补旧番","n":7601,"i":651},{"t":"番組WIKI計画","n":5384,"i":128},{"t":"nico旁观者","n":4564,"i":34},{"t":"我们就爱acfun","n":4174,"i":39},{"t":"宽带综合症候群","n":3758,"i":35},{"t":"正经向里番交流讨论","n":3026,"i":3938},{"t":"伪春菜","n":2930,"i":6},{"t":"愛撕衣的后花園","n":2759,"i":28},{"t":"站务论坛","n":2472,"i":2},{"t":"日本語","n":1976,"i":202},{"t":"天窗联盟 - 寄卖、合摊宣传版","n":1404,"i":822},{"t":"GALGAME","n":983,"i":610},{"t":"天窗联盟讨论版","n":874,"i":609},{"t":"不晒桌面就会死星人","n":849,"i":314},{"t":"番组开发","n":766,"i":4180},{"t":"哔哩哔哩 - ( ゜- ゜)つロ 乾杯~","n":756,"i":454},{"t":"Bangumi 应援","n":751,"i":222},{"t":"同人与原创绘师。","n":675,"i":216},{"t":"评分与排名讨论会","n":600,"i":3967},{"t":"「小圣杯」最萌大战","n":593,"i":4294},{"t":"弃置中","n":550,"i":223},{"t":"胡思乱想团","n":541,"i":729},{"t":"不专业糟糕漫画研究","n":540,"i":3905},{"t":"etokei 绘时计","n":532,"i":511},{"t":"X癖大观","n":513,"i":4312},{"t":"盗墓笔记","n":512,"i":619},{"t":"Twitter","n":508,"i":235},{"t":"bangumi 新入生歓迎会（公关部）","n":495,"i":446},{"t":"不靠谱人生茶话会","n":447,"i":4409},{"t":"GOOGLE+","n":428,"i":780},{"t":"天窗联盟 - 印刷宣传版","n":426,"i":821},{"t":"班固米做菜人","n":411,"i":4324},{"t":"W.E.O. 世界黄油组织","n":391,"i":1315},{"t":"onAir","n":371,"i":797},{"t":"用户脚本 · 样式 · 插件","n":359,"i":4116},{"t":"大龄班固米","n":334,"i":4125},{"t":"他喵的，传说中的里屋。","n":304,"i":54},{"t":"煎茶组","n":303,"u":"kitt"},{"t":"Bangumi星空計画","n":293,"i":1196},{"t":"饮料测评","n":290,"i":3976},{"t":"BILIBILI吧","n":288,"i":1424},{"t":"新番咖啡厅","n":283,"i":4483},{"t":"【碧姬文库】Bangumi文库","n":282,"i":1380},{"t":"求圖問歌找出處","n":278,"i":980},{"t":"游戏研究会","n":272,"i":4130},{"t":"PT交流","n":258,"i":4424},{"t":"Indie Spirits　／　独立精神","n":258,"i":3985},{"t":"BUG 追踪","n":251,"i":433},{"t":"DOLLARS","n":238,"i":428},{"t":"垃圾桶","n":231,"i":4456},{"t":"yande.re","n":226,"i":218},{"t":"远子学姐的三题点心","n":213,"i":4082},{"t":"南京同城会","n":208,"i":613},{"t":"Nintendo Switch","n":204,"i":4161},{"t":"Bangumi 北美交流面基团","n":196,"i":4118},{"t":"招募集散地","n":195,"i":1010},{"t":"今天我特么的想报复射会","n":187,"i":1208},{"t":"Chrome","n":187,"i":436},{"t":"日语学习","n":184,"i":343},{"t":"NPC酱的bangumi常识教室","n":182,"i":805},{"t":"壁吧小分队","n":177,"u":"mingzuozhibi"},{"t":"我可能好乙女游戏这一口","n":177,"i":604},{"t":"写作与翻译练习","n":175,"i":4374},{"t":"班固米老年人活动中心","n":171,"i":4076},{"t":"闲置物品","n":166,"i":1115},{"t":"osu!","n":161,"i":577},{"t":"读书会","n":158,"i":1292},{"t":"Galgamer","n":154,"i":3880},{"t":"新番动漫音乐","n":150,"i":243},{"t":"Bangumi番组计划 for Android（暂）","n":148,"i":1256},{"t":"PSP飯","n":148,"i":250},{"t":"字體硏究","n":147,"i":1495},{"t":"班咕咪姛画片同好会","n":146,"i":4529},{"t":"ACG音乐演奏的魅力","n":146,"i":3817},{"t":"bangumi帝都搅基预备团","n":141,"i":491},{"t":"爱做梦","n":140,"i":817},{"t":"黑长直","n":138,"i":496},{"t":"国产ACG推广协会","n":136,"i":919},{"t":"Axis powers ヘタリア","n":134,"i":247},{"t":"轻小说组","n":134,"i":224},{"t":"非日常读书小组","n":131,"i":4204},{"t":"东方幻想乡","n":131,"u":"dongfanghuanxiangxiang"},{"t":"瓶邪","n":131,"i":638},{"t":"华语第四","n":129,"i":3804},{"t":"嗶哩嗶哩 ( ゜- ゜)つロ 乾杯~","n":126,"i":983},{"t":"3DS","n":125,"i":540},{"t":"Falcom","n":125,"i":220},{"t":"Sai捣乱团！","n":125,"i":201},{"t":"Key社应援会","n":125,"i":68},{"t":"监督控","n":123,"i":246},{"t":"eMule联盟","n":122,"i":181},{"t":"某漫研的整理目录","n":120,"i":811},{"t":"エロゲ学研部","n":119,"i":650},{"t":"对这好片被埋没的时代绝望了","n":118,"i":1390},{"t":"VOCALOID系列","n":118,"i":180},{"t":"写作win10念作microsoft","n":117,"i":4018},{"t":"bangumi房事交流体验小组","n":116,"i":4392},{"t":"妹控","n":116,"i":342},{"t":"東方Project","n":116,"i":132},{"t":"PSVita","n":115,"i":1116},{"t":"SAI","n":115,"i":623},{"t":"番組美术","n":113,"i":3752},{"t":"魔都群众联谊会","n":113,"i":525},{"t":"花泽香菜","n":113,"i":472},{"t":"萌否","n":111,"i":522},{"t":"我们都是不和谐的冷场帝","n":110,"i":789},{"t":"幻想郷","n":110,"i":95},{"t":"泡麺测评","n":109,"i":4053},{"t":"伪宅人生商谈茶话会","n":109,"i":672},{"t":"身为学生狗啊千言万语其实也并没有那么多会呼吸的痛嘴上说着会好好努力结果还是做这做那懒癌拒疗","n":107,"i":3988},{"t":"TORA酱应援-JS同萌团","n":107,"i":513},{"t":"～普通用户压力大～","n":105,"i":500},{"t":"博丽神社后仓库","n":105,"i":471},{"t":"Sound Horizon","n":105,"i":147},{"t":"nbht声豚同好会","n":104,"i":4273},{"t":"健康生活忏悔室","n":103,"i":4250},{"t":"bilibili,ばんざい!","n":103,"i":630},{"t":"收图党","n":103,"i":230},{"t":"晒晒更健康","n":103,"i":199},{"t":"神谷浩史","n":102,"i":562},{"t":"中村明日美子","n":100,"i":656},{"t":"腐女子聚集地","n":99,"i":249},{"t":"少数派新番研究小组","n":97,"i":694},{"t":"MAGI 问答","n":97,"i":689},{"t":"废柴2","n":97,"i":379},{"t":"杉田智和~~!我们是一辈子吐槽控,没错~","n":96,"i":339},{"t":"Nitro+CHiRAL症候群","n":96,"i":203},{"t":"KeyFansClub同好会","n":95,"i":92},{"t":"型月社","n":94,"i":10},{"t":"Wordpress","n":93,"i":234},{"t":"McFog's Bangumi Plugin","n":92,"i":606},{"t":"Google Reader Holics","n":92,"i":593},{"t":"Firefox","n":92,"i":260},{"t":"饭否","n":89,"i":560},{"t":"三次元PVC小组","n":89,"i":195},{"t":"耳朵要怀孕了混蛋！","n":88,"i":590},{"t":"动漫集中营","n":87,"i":872},{"t":"ACG食物记","n":87,"i":851},{"t":"地球毁灭委员会","n":87,"i":426},{"t":"Buzz","n":87,"i":409},{"t":"BGM38楽屋","n":86,"i":1299},{"t":"Steam","n":86,"i":838},{"t":"黑猫党","n":85,"i":570},{"t":"挖","n":84,"i":1356},{"t":"下半身","n":84,"i":725},{"t":"初音miku后援团","n":84,"i":88},{"t":"Android","n":83,"i":612},{"t":"中二病","n":83,"i":548},{"t":"番組娘化 ver.4","n":82,"i":1504},{"t":"番組设计","n":80,"i":1410},{"t":"Lolicon","n":79,"i":63},{"t":"瓶邪","n":78,"i":695},{"t":"Sound Horizon","n":78,"i":345},{"t":"neta","n":77,"i":1151},{"t":"NPC酱的bangumi应援会","n":77,"i":806},{"t":"海外党","n":77,"u":"overseas"},{"t":"花泽病患集中地","n":77,"i":410},{"t":"釘宮理恵","n":75,"i":445},{"t":"追新番","n":75,"i":274},{"t":"虚淵玄","n":75,"i":171},{"t":"音游玩家交流","n":74,"i":4371},{"t":"二次元就是三次元的我剥掉一层名为节操的皮","n":74,"i":1562},{"t":"日本生活","n":74,"i":922},{"t":"Ubuntu","n":74,"i":431},{"t":"魔都ACG","n":74,"i":359},{"t":"逆转监督带领的闪电11足球骑士和队长翼在哨声响起时向银河开球掀起了一阵足球风云再见了克拉默 教练，","n":73,"i":1189},{"t":"零食评测小屋【食べ物】","n":72,"i":3999},{"t":"Catfan 喵友 - 同好会","n":72,"i":818},{"t":"Bangumi 神秘花园","n":72,"u":"bangumi_garden"},{"t":"山田一&田中ロミオ","n":72,"i":107},{"t":"唱见/术力口研究室","n":71,"i":4453},{"t":"東方同人音楽補完計画","n":71,"i":660},{"t":"拔作研","n":70,"i":4433},{"t":"BGM放映室","n":70,"i":4345},{"t":"音楽の幻想郷","n":70,"i":677},{"t":"Ingress","n":69,"i":1332},{"t":"(bgm38)","n":69,"i":929},{"t":"绘画交流小组","n":69,"i":514},{"t":"樱井孝宏","n":69,"i":423},{"t":"Lucky☆Star后援同好会","n":69,"i":196},{"t":"早睡早起促进会","n":68,"i":4290},{"t":"中老年健康作息","n":68,"i":1322},{"t":"黑暗料理屋","n":68,"i":547},{"t":"中村悠一","n":68,"i":338},{"t":"流浪S1漫区","n":67,"i":4305},{"t":"在这个偌大的世界 -","n":67,"i":814},{"t":"焗长","n":67,"i":724},{"t":"饅頭卡教","n":66,"i":687},{"t":"锡安山同好会","n":66,"i":55},{"t":"小野大辅","n":65,"i":563},{"t":"广州搬谷米团","n":65,"i":486},{"t":"哥哥 有像果冻一样滑滑的东西射进我里面啦!!","n":64,"i":1612},{"t":"故事接龙","n":64,"i":1420},{"t":"今天也好伤心","n":64,"i":1187},{"t":"今天也沒有…","n":64,"i":916},{"t":"树洞不","n":64,"i":765},{"t":"反腐倡宅联盟","n":64,"i":758},{"t":"放牛班","n":64,"i":625},{"t":"马G赛F克W&马翻赛墙克术研究","n":64,"u":"gfw"},{"t":"Hentai魔导","n":63,"i":4011},{"t":"我们都爱洗衣机","n":63,"i":661},{"t":"博麗神社","n":63,"i":456},{"t":"Apple User","n":62,"i":24},{"t":"新海誠","n":61,"i":154},{"t":"BGM漫画同好会","n":60,"i":4455},{"t":"京都动画","n":60,"i":4028},{"t":"繪畫新手村","n":60,"i":1378},{"t":"Macintosh","n":60,"i":390},{"t":"震惊协会","n":60,"i":57},{"t":"甜蜜的宅式政治派对","n":60,"i":16},{"t":"作業去死去團","n":59,"i":529},{"t":"Game Over","n":59,"i":477},{"t":"坂本真绫","n":59,"i":332},{"t":"菅野よう子","n":59,"i":192},{"t":"Explorareの隔离病栋","n":58,"i":4022},{"t":"犯罪方法调研会","n":58,"u":"criminal"},{"t":"新房昭之","n":58,"i":681},{"t":"杭州御宅基地（又名H天堂。。orz。。。","n":58,"i":533},{"t":"梶浦由記ファミリー","n":58,"i":335},{"t":"幻想乡观光团","n":58,"i":67},{"t":"SONY-PSP","n":58,"i":30},{"t":"批评空间","n":57,"i":1723},{"t":"超自然研究会","n":57,"i":875},{"t":"恶意卖萌小分队","n":57,"i":452},{"t":"百合","n":57,"i":47},{"t":"今天的bgm38","n":56,"i":1176},{"t":"WAVE","n":56,"i":375},{"t":"能登麻美子","n":56,"i":219},{"t":"逆転裁判所","n":56,"i":137},{"t":"群友们该看了","n":55,"i":4207},{"t":"我们都爱阴X君","n":54,"i":782},{"t":"小小姑娘 早早起床","n":54,"i":678},{"t":"nds特工队","n":54,"i":321},{"t":"石田彰~彰鱼们的部屋~","n":53,"i":634},{"t":"日英⇌中翻译能力向上小组","n":52,"i":4362},{"t":"Bangumi娘语录","n":52,"i":1553},{"t":"二手同人本交易平台","n":52,"i":1269},{"t":"非正常人类研究中心","n":52,"i":713},{"t":"天然卷的男人都是好男人","n":52,"i":647},{"t":"凡事本地盘","n":52,"i":217},{"t":"杉田智和","n":52,"i":177},{"t":"瀬戸口廉也（唐辺葉介）","n":52,"i":104},{"t":"这都是因为年轻犯下的错 啊","n":51,"i":1175},{"t":"谁都有个拖延症！","n":51,"i":696},{"t":"VOCALOID","n":51,"u":"vocaloid"},{"t":"BlueInk","n":51,"i":56},{"t":"天然呆的自我反省教室","n":50,"i":1211},{"t":"生活真美好","n":50,"i":798},{"t":"Clean & Clear","n":50,"i":587},{"t":"诚哥你是我一生的偶像","n":50,"i":495},{"t":"萌战","n":50,"i":478},{"t":"deviantART","n":50,"i":432},{"t":"声控同萌会","n":50,"i":322},{"t":"ニコニコ動画","n":50,"i":261},{"t":"离谱人生茶话会","n":49,"i":4411},{"t":"PKU-GAL","n":49,"i":4145},{"t":"异端审问会","n":49,"i":1263},{"t":"都市传说","n":49,"i":819},{"t":"澄空学园大食堂","n":49,"i":443},{"t":"不可回收垃圾聚集地","n":48,"i":4330},{"t":"东方project","n":48,"i":4005},{"t":"早","n":48,"i":1237},{"t":"年糕伯爵協會-v-","n":48,"i":73},{"t":"明日方舟","n":47,"i":4277},{"t":"滚去背单词！","n":47,"i":1623},{"t":"Key","n":47,"i":1340},{"t":"您现在还蛋疼吗，乳酸菌？","n":47,"i":501},{"t":"Jsharer","n":47,"i":262},{"t":"哆啦A梦","n":47,"i":58},{"t":"iPhone","n":47,"i":42},{"t":"什么值得买","n":46,"i":4449},{"t":"求是潮","n":46,"i":3798},{"t":"07thExpansion 寒蝉海猫同好会","n":46,"i":333},{"t":"机战世界","n":46,"i":82},{"t":"去死去死团","n":46,"i":48},{"t":"Opera","n":45,"i":437},{"t":"H王道内部交流","n":45,"i":254},{"t":"杉田智和吐槽集中营","n":44,"i":645},{"t":"APH露中党聚集地","n":44,"i":639},{"t":"MUJI無印良品","n":44,"i":481},{"t":"黑之契约者","n":44,"i":184},{"t":"Liar-soft（ライアーソフト）","n":44,"i":106},{"t":"三十天推番挑战","n":43,"i":4281},{"t":"E绅士@BGM","n":43,"i":1312},{"t":"占","n":43,"i":1141},{"t":"NitroPlus（ニトロプラス）","n":43,"i":103},{"t":"武汉acg同好会","n":43,"i":96},{"t":"bgm戒色小组","n":42,"i":4544},{"t":"Chi: Bangumi 未来实验室","n":42,"i":3975},{"t":"My World, Your Universe","n":42,"i":3940},{"t":"VeryCD","n":42,"i":518},{"t":"伪娘·伪百合","n":42,"i":366},{"t":"読書総合病院","n":41,"i":4301},{"t":"资源发布同好会><!!!","n":41,"i":1197},{"t":"我们都是剧透党","n":41,"i":931},{"t":"UNIQLO优衣库","n":41,"i":444},{"t":"魔神劍！虎牙破斬！以下省略=NAMCO傳説系列COMMU=","n":41,"i":373},{"t":"Google","n":41,"i":280},{"t":"NTR爱好者","n":40,"i":4372},{"t":"压制组选择","n":40,"i":4080},{"t":"加入这个小组 你就会变得很有钱","n":40,"i":4029},{"t":"EVA","n":40,"u":"eva"},{"t":"我们的事业是正义的","n":40,"i":25},{"t":"社会垃圾互助谐会","n":39,"i":4239},{"t":"完结动漫研究组","n":39,"i":1626},{"t":"科幻","n":39,"i":1273},{"t":"Type-Moon","n":39,"i":718},{"t":"NMM Café","n":39,"i":568},{"t":"閃電十一人","n":39,"i":566},{"t":"魔兽世界","n":39,"i":498},{"t":"StarCraft研讨会","n":39,"i":459},{"t":"平淡的活着","n":38,"i":3980},{"t":"PS4","n":38,"i":1546},{"t":"今天我要用正面力量拯救射会","n":38,"i":1257},{"t":"京都動畫","n":38,"i":549},{"t":"おおきく振りかぶって！","n":38,"i":487},{"t":"clamp","n":38,"i":349},{"t":"萝莉天堂","n":37,"i":4498},{"t":"世萌","n":37,"i":3749},{"t":"小透明の养成计划","n":37,"i":1444},{"t":"那些浪费的和正在浪费着的以及未来等待我去浪费的时光","n":37,"i":1418},{"t":"耳机","n":37,"i":874},{"t":"铃村健一","n":37,"i":543},{"t":"諏訪部順一","n":37,"i":251},{"t":"同人音乐","n":37,"u":"cm"},{"t":"Mabinogi","n":37,"i":49},{"t":"寻番の侦探事务所","n":36,"i":4297},{"t":"galgame喜好小组","n":36,"i":4124},{"t":"ENDCARD","n":36,"i":3751},{"t":"新番交流会","n":36,"i":1586},{"t":"考据癖","n":36,"i":928},{"t":"自定义和萌化","n":36,"i":777},{"t":"就喜欢摆张残念的脸","n":36,"i":581},{"t":"新房是个大BT","n":36,"i":204},{"t":"游戏音乐","n":36,"i":174},{"t":"ACGSH","n":35,"u":"acgsh"},{"t":"手绘什么的有爱！","n":35,"i":1376},{"t":"大家都有中二病☆","n":35,"i":1291},{"t":"广告专区(纯发广告)","n":35,"i":1174},{"t":"時間線演劇部","n":35,"i":852},{"t":"test","n":35,"i":536},{"t":"团子大家族","n":35,"i":399},{"t":"——","n":35,"i":309},{"t":"空知英秋","n":35,"i":178},{"t":"打麻将真开心啊","n":34,"i":4121},{"t":"东方project","n":34,"u":"df"},{"t":"嘀咕","n":34,"i":602},{"t":"南京ACG同好","n":34,"i":356},{"t":"Shining动漫社远征团","n":34,"i":245},{"t":"动画福利收集","n":33,"i":4378},{"t":"DD 学校","n":33,"i":4268},{"t":"DD","n":33,"i":4168},{"t":"長者粉絲團","n":33,"u":"elderfans"},{"t":"福山润","n":33,"i":1527},{"t":"大家一起看电影","n":33,"u":"reoblue"},{"t":"二次伪娘同好会","n":33,"i":597},{"t":"就爱看冷门","n":33,"i":595},{"t":"成都Comiday","n":33,"i":572},{"t":"游戏王","n":33,"i":464},{"t":"PlayStation 3","n":33,"i":429},{"t":"观铃最高亲卫队","n":33,"i":93},{"t":"放 映 協 會","n":32,"i":4234},{"t":"九重凛的四次元口袋","n":32,"i":4210},{"t":"[游戏创作]東方坦克幻（暂定）","n":32,"i":1561},{"t":"哲学家 & 哲♂学♂家","n":32,"i":850},{"t":"轻口味H研究院","n":32,"i":748},{"t":"Flickr","n":32,"i":539},{"t":"Facebook","n":32,"i":523},{"t":"KAITO大哥爱!!","n":32,"i":374},{"t":"minori","n":32,"i":256},{"t":"MACROSS F 女王党","n":32,"i":14},{"t":"女权文章摘抄中心","n":31,"u":"feminism"},{"t":"我有一个逆天的问题","n":31,"i":1497},{"t":"里妹输入法 rimeime","n":31,"i":1228},{"t":"克苏鲁神话同好会","n":31,"i":876},{"t":"百合同萌","n":31,"i":682},{"t":"夜猫子","n":31,"i":567},{"t":"GALGame爱好者","n":31,"i":483},{"t":"illusion","n":31,"i":465},{"t":"aph同萌会","n":31,"i":453},{"t":"子安武人","n":31,"i":422},{"t":"宝井理人「Licht」","n":31,"i":380},{"t":"推倒米人协会","n":31,"i":319},{"t":"东方绯想天","n":31,"i":257},{"t":"志方あきこ","n":31,"i":238},{"t":"既然有愛撕衣的后花园那也建一个破沟的后花园好了。","n":31,"i":236},{"t":"一首歌的时间讲一个故事","n":30,"i":4200},{"t":"Linux","n":30,"i":1515},{"t":"SCP Foundation","n":30,"i":1224},{"t":"腐向爱好者聚集地","n":30,"u":"hjjj2011"},{"t":"作画崩坏 － 作画监督号称自己是无辜的！","n":30,"i":607},{"t":"少年同盟","n":30,"i":488},{"t":"avatar降世神通好盆友聚集地","n":30,"i":377},{"t":"就爱BDRip","n":30,"i":324},{"t":"星空めてお","n":30,"i":160},{"t":"浦沢直樹","n":30,"i":134},{"t":"Hong Kong","n":29,"i":3970},{"t":"轻小说推荐组","n":29,"i":1459},{"t":"打油诗","n":29,"i":956},{"t":"好好早起团","n":29,"i":912},{"t":"考試","n":29,"i":771},{"t":"现代百合搞基文学研究组","n":29,"i":632},{"t":"SoundHorizon幻想楽団中国应援会","n":29,"i":628},{"t":"cc98的后门","n":29,"i":589},{"t":"梶裕贵","n":29,"i":564},{"t":"成都宅腐勾搭调教群","n":29,"i":360},{"t":"東方非想天則","n":29,"i":317},{"t":"I've Sound","n":29,"u":"ive"},{"t":"御姐控","n":29,"i":86},{"t":"Xbox360萌","n":29,"i":13},{"t":"零食吃到饱","n":28,"i":4473},{"t":"竹子同好会","n":28,"i":4432},{"t":"python","n":28,"i":4155},{"t":"黄油和艺术","n":28,"i":3895},{"t":"自言自语。","n":28,"i":1304},{"t":"成田老师快去睡觉！","n":28,"i":629},{"t":"sosg","n":28,"i":558},{"t":"我們都是魔法師！","n":28,"i":551},{"t":"とある科学の超電磁砲","n":28,"i":419},{"t":"wiki条目修正小组","n":28,"i":233},{"t":"武内崇","n":28,"i":168},{"t":"现视研","n":28,"i":66},{"t":"Comic_Market","n":28,"i":37},{"t":"创建者极其懒惰偏激加有病的自闭外国米姆（meme）研究会","n":27,"i":3753},{"t":"比特币","n":27,"i":1481},{"t":"纸模量产工坊","n":27,"i":1195},{"t":"九号楼的考米克","n":27,"i":933},{"t":"花开伊吕波","n":27,"i":824},{"t":"乙女向同好会","n":27,"i":787},{"t":"茅原実里","n":27,"i":473},{"t":"文学社","n":27,"i":469},{"t":"乾物女","n":27,"i":370},{"t":"BAKUMAN！！","n":27,"i":362},{"t":"TONY神殿","n":27,"i":69},{"t":"神奈川冲浪里","n":26,"i":4521},{"t":"自由软件","n":26,"u":"foss"},{"t":"东京线下会","n":26,"i":4159},{"t":"少女前线指挥活动中心","n":26,"i":4139},{"t":"前端开发","n":26,"i":3770},{"t":"推理小说","n":26,"u":"trick"},{"t":"五月病作者协会","n":26,"i":781},{"t":"綠川光","n":26,"i":701},{"t":"妖都同城搞基會","n":26,"u":"guangzhougj"},{"t":"腐的品格","n":26,"i":515},{"t":"佐天泪子亲卫队","n":26,"i":416},{"t":"茶太","n":26,"i":208},{"t":"るーすぼーい","n":26,"i":120},{"t":"大爱霹雳（—v—）~~","n":26,"i":4},{"t":"USTC-GALGAME","n":25,"i":4435},{"t":"大好男娘","n":25,"i":4205},{"t":"茅野爱衣","n":25,"i":1619},{"t":"黒い童話","n":25,"i":1552},{"t":"Minecraft","n":25,"i":1366},{"t":"远东魔术昼寝结社","n":25,"i":1297},{"t":"自爆","n":25,"i":1274},{"t":"东方project","n":25,"i":719},{"t":"邪瓶","n":25,"i":684},{"t":"萝莉推倒计划","n":25,"i":584},{"t":"无差别怪奇事务所","n":25,"u":"hsoul"},{"t":"麻将部","n":25,"i":467},{"t":"东方高校第⑨培训基地","n":25,"i":205},{"t":"Leaf Saimoe Club","n":25,"i":113},{"t":"绝对领域","n":25,"i":27},{"t":"班谷米尼(安德)特人","n":24,"i":4557},{"t":"嘉然的嘉心糖粉丝小组","n":24,"i":4476},{"t":"「いつか忘れる本の題名」","n":24,"i":1443},{"t":"soundcloud推荐","n":24,"i":1391},{"t":"漫画组","n":24,"i":1264},{"t":"Tora醬の貓電磁炮","n":24,"i":854},{"t":"假面骑士","n":24,"i":592},{"t":"clear","n":24,"i":462},{"t":"A.I.R.nesSub","n":24,"u":"airu"},{"t":"绫波丽fans聚集地","n":24,"i":355},{"t":"伸手黨","n":24,"i":340},{"t":"OKAMA","n":24,"i":145},{"t":"Bangumi立直麻将研究会","n":23,"i":4404},{"t":"闲聊","n":23,"i":4084},{"t":"松冈爱衣催婚协会","n":23,"i":4030},{"t":"Bangumi 匿名版","n":23,"u":"anonymous"},{"t":"单机游戏组","n":23,"i":1296},{"t":"怪物猎人","n":23,"i":1253},{"t":"才、才不是M属性呢","n":23,"i":1217},{"t":"谷娘插入中……","n":23,"i":920},{"t":"水树奈々","n":23,"i":803},{"t":"不和谐的H交汇之处","n":23,"i":788},{"t":"组队卖萌","n":23,"i":599},{"t":"沢城みゆき","n":23,"i":497},{"t":"世界杯","n":23,"i":458},{"t":"300少女的秘密基地","n":23,"i":457},{"t":"疼迅微博","n":23,"i":440},{"t":"只有神知道的世界","n":23,"i":425},{"t":"Share","n":23,"i":404},{"t":"MADhouse","n":23,"i":397},{"t":"豆瓣er的后庭园盛开着野菊","n":23,"u":"douban"},{"t":"寂寞","n":23,"i":229},{"t":"COMIC LO","n":23,"i":156},{"t":"水樹奈々","n":23,"i":133},{"t":"机动战士联盟","n":23,"i":91},{"t":"乌龟饲养繁殖心得交流组","n":22,"i":4414},{"t":"彩虹人","n":22,"i":4343},{"t":"KDE","n":22,"i":3876},{"t":"马尾力","n":22,"i":3807},{"t":"A岛","n":22,"i":3775},{"t":"RP君想出本子TwT","n":22,"i":1446},{"t":"Bangumi Windows phone 客户端","n":22,"i":1132},{"t":"国番搬运组","n":22,"i":958},{"t":"inTouch","n":22,"i":887},{"t":"豐崎愛生","n":22,"i":600},{"t":"ARIA COMPANY","n":22,"i":576},{"t":"tumblr","n":22,"i":574},{"t":"宅男宅女勾搭群","n":22,"i":534},{"t":"团子大家族","n":22,"i":455},{"t":"封神","n":22,"i":225},{"t":"理多（Rita）","n":22,"i":105},{"t":"太鼓の達人","n":22,"i":43},{"t":"DS最萌","n":22,"i":23},{"t":"BGM减肥交流小组","n":21,"i":4391},{"t":"天体観測","n":21,"u":"astrophy"},{"t":"井上敏鬼保护协会","n":21,"i":4229},{"t":"坎巴拉太空计划","n":21,"i":3978},{"t":"南泽十八研究会","n":21,"i":1693},{"t":"耽美社","n":21,"i":1629},{"t":"深圳ACG同好面基团~","n":21,"i":1293},{"t":"马克思主义理论研究","n":21,"i":923},{"t":"Nintendo","n":21,"i":763},{"t":"败家子反省会","n":21,"i":739},{"t":"DJMAX讨论区","n":21,"i":504},{"t":"AKB48応援団","n":21,"i":485},{"t":"GONZO","n":21,"i":331},{"t":"——","n":21,"i":325},{"t":"平野绫","n":21,"i":228},{"t":"Eushully-chan room","n":21,"i":75},{"t":"柠檬研究所","n":20,"i":4363},{"t":"妹控","n":20,"i":4352},{"t":"只有二十点五加减半个人的小组","n":20,"i":4347},{"t":"BangumiN","n":20,"i":4276},{"t":"日常","n":20,"i":4203},{"t":"京蜜京蜜京","n":20,"i":4043},{"t":"SOS团","n":20,"i":3981},{"t":"哆啦A萌","n":20,"u":"duolaameng"},{"t":"Bubble闲聊室","n":20,"u":"bubble"},{"t":"宫野真守","n":20,"i":1601},{"t":"摄影","n":20,"i":1496},{"t":"蒸汽基","n":20,"i":820},{"t":"Pokémon","n":20,"i":762},{"t":"长沙同城acg爱好者联合会","n":20,"i":720},{"t":"邻人部","n":20,"i":675},{"t":"宅度测试","n":20,"i":673},{"t":"云计算","n":20,"i":527},{"t":"临静","n":20,"i":489},{"t":"カズアキ「K E100S」","n":20,"i":460},{"t":"我们都是笨蛋召唤受","n":20,"i":420},{"t":"Project Tomodachi","n":20,"u":"tomodachi"},{"t":"辽宁省ACGer同好会","n":20,"u":"liaoning"},{"t":"H-comic","n":20,"i":276},{"t":"Innocent Grey","n":20,"i":173},{"t":"Pokemon同人交流","n":20,"i":163},{"t":"村田蓮爾","n":20,"i":143},{"t":"あかべぇそふとつぅ（AKABEiSOFT2）","n":20,"i":118},{"t":"少女と猫同萌会","n":20,"i":94},{"t":"真三国无双~！","n":20,"i":7},{"t":"シャニマス","n":19,"i":4468},{"t":"元火bgm","n":19,"i":4246},{"t":"Java","n":19,"i":4132},{"t":"☆世界动画短片鉴赏★","n":19,"i":4055},{"t":"请给我一打好故事","n":19,"i":1568},{"t":"好好说话就会死星人","n":19,"i":1542},{"t":"SAI情報交流所","n":19,"i":1423},{"t":"林卯綱目","n":19,"i":886},{"t":"API","n":19,"i":808},{"t":"丸戸史明","n":19,"i":121},{"t":"Littlewitch","n":19,"i":101},{"t":"在魔都的中心呼唤宅","n":19,"i":74},{"t":"网络侦探组","n":18,"i":4518},{"t":"null","n":18,"u":"littlesoftware"},{"t":"冈学","n":18,"i":4243},{"t":"云中GalGame交流茶会","n":18,"i":4235},{"t":"媒体播放器","n":18,"i":4136},{"t":"舰队collection","n":18,"i":4061},{"t":"虾米音乐","n":18,"i":3766},{"t":"画师Hidari_左","n":18,"i":1474},{"t":"无限轮回系列","n":18,"i":1294},{"t":"一起渣剑网三的日子","n":18,"i":1244},{"t":"鄰人部","n":18,"i":975},{"t":"兄贵","n":18,"i":690},{"t":"斎藤千和","n":18,"i":580},{"t":"YY观光团","n":18,"i":541},{"t":"Wordpress求交往小组","n":18,"i":526},{"t":"鈴木達央","n":18,"i":438},{"t":"川澄綾子 X 能登麻美子","n":18,"i":421},{"t":"河下水希","n":18,"i":369},{"t":"-","n":17,"u":"jiba114514"},{"t":"班固米算法学社","n":17,"i":4386},{"t":"同人小说设计交流","n":17,"i":3891},{"t":"acg翻唱音乐控","n":17,"i":3875},{"t":"ひまわり動画","n":17,"i":1179},{"t":"茶话会番组计划","n":17,"u":"boringbangumi"},{"t":"٩ʕ•͡×•ʔ 。哎嘿。屯个地方","n":17,"i":1165},{"t":"坂本真绫","n":17,"i":869},{"t":"acl fans","n":17,"i":605},{"t":"大叔同好会","n":17,"i":583},{"t":"下野紘","n":17,"i":565},{"t":"中井和哉","n":17,"i":535},{"t":"May'n","n":17,"i":479},{"t":"黑色骑士团","n":17,"i":382},{"t":"鈴木達央~タツオ症候群","n":17,"i":378},{"t":"手机拟人计划","n":17,"u":"mobileson"},{"t":"已作废小组","n":17,"i":237},{"t":"Bones骨头社","n":16,"i":4079},{"t":"百合控在此！","n":16,"i":4020},{"t":"人间动物园","n":16,"i":4009},{"t":"田口宏子","n":16,"i":3979},{"t":"已弃疗 未吃药","n":16,"i":3781},{"t":"高桥优（たかはし ゆう/Takahashi Yuu）","n":16,"u":"gaoqiaoyou"},{"t":"喜多村英梨","n":16,"i":1261},{"t":"Bangumi Subtitles","n":16,"u":"bangumi_subtitles"},{"t":"动漫研究部","n":16,"i":1192},{"t":"重庆ACG同好会~","n":16,"i":1167},{"t":"wp7","n":16,"i":961},{"t":"Last.Exile","n":16,"i":948},{"t":"SCCN bangumi愛好者","n":16,"i":877},{"t":"VOC@LOiD NETWORK","n":16,"i":785},{"t":"bangumi澳大利亚作战指挥部","n":16,"i":752},{"t":"南方公园","n":16,"i":743},{"t":"指尖奶茶应援会","n":16,"i":617},{"t":"抖M专用","n":16,"i":555},{"t":"Gero","n":16,"i":550},{"t":"珠海Bangumi应援团","n":16,"i":528},{"t":"多元宇宙研究会","n":16,"i":448},{"t":"命令与征服","n":16,"i":411},{"t":"川澄绫子","n":16,"i":226},{"t":"中原麻衣","n":16,"i":209},{"t":"冬目景","n":16,"i":140},{"t":"Suara同好会","n":16,"i":45},{"t":"电子竞技播映厅","n":15,"i":4275},{"t":"九羽鸟庵","n":15,"i":4122},{"t":"看動漫1000部以上的少女","n":15,"i":4006},{"t":"铁甲依然在","n":15,"i":3937},{"t":"大天柴吃鱼俱乐部","n":15,"u":"l2180"},{"t":"求GD集散地","n":15,"i":1680},{"t":"进击的巨人","n":15,"i":1518},{"t":"人世间的乐趣","n":15,"i":1513},{"t":"一起来做视频吧！","n":15,"i":1467},{"t":"婚恋育儿","n":15,"u":"hunlian"},{"t":"上海西南某高校","n":15,"i":1361},{"t":"深夜人参相谈会","n":15,"u":"shenye"},{"t":"CP越冷越爱","n":15,"i":1317},{"t":"中村悠一同好会","n":15,"i":1190},{"t":"noitaminA","n":15,"i":1150},{"t":"小黑屋","n":15,"i":1021},{"t":"英雄联盟","n":15,"u":"lol"},{"t":"古都西安基友团","n":15,"i":706},{"t":"安元洋貴","n":15,"i":702},{"t":"トゥライ=minato=流星P","n":15,"i":544},{"t":"ATLUS","n":15,"i":538},{"t":"Futurama 飞出个未来","n":15,"i":435},{"t":"小清水亚美","n":15,"i":427},{"t":"三次元去死去死团","n":15,"i":385},{"t":"EVE","n":15,"i":344},{"t":"淺蔥の神社","n":15,"i":221},{"t":"Stand Alone Complex","n":15,"i":193},{"t":"THE IDOLM@STER","n":15,"i":146},{"t":"中央東口","n":15,"i":136},{"t":"いとうかなこ","n":15,"i":135},{"t":"Dota","n":15,"i":129},{"t":"Girls' Work","n":15,"i":114},{"t":"综合嫌味组","n":15,"i":98},{"t":"噶哦_key","n":15,"i":8},{"t":"Perfect Blue","n":15,"u":"pb"},{"t":"本子分享","n":14,"i":4556},{"t":"ロリコン","n":14,"i":4539},{"t":"运动减脂增肌打卡，战胜惰性。","n":14,"u":"muscle"},{"t":"摇滚乐","n":14,"i":4146},{"t":"萌豚养豚场","n":14,"i":4119},{"t":"二次元番剧游戏gal交流小组","n":14,"i":4111},{"t":"P.A.WORKS","n":14,"i":4099},{"t":"同人本插画、封面","n":14,"u":"oriharaanko"},{"t":"彼方的晓之水平线～","n":14,"i":3986},{"t":"轮回内销传播组","n":14,"u":"samsara"},{"t":"平川大辅","n":14,"i":3897},{"t":"初音未来","n":14,"i":1647},{"t":"车欠女未","n":14,"i":1503},{"t":"《梦想钱包》（轻小说）{一起来写轻小说吧！}","n":14,"i":1334},{"t":"寻冷番","n":14,"i":1251},{"t":"新番综合","n":14,"u":"seasons"},{"t":"宝井理人[资源组]","n":14,"i":1137},{"t":"2D格斗游戏同好","n":14,"i":1128},{"t":"BAN娘的万智牌中心","n":14,"i":843},{"t":"acg米国作战总部","n":14,"i":807},{"t":"死んだ世界戦線","n":14,"i":728},{"t":"竹達彩奈","n":14,"i":668},{"t":"伊东杂音（いとうのいぢ）","n":14,"i":659},{"t":"海贼王 ONE PIECE","n":14,"i":649},{"t":"杭州声优控","n":14,"i":398},{"t":"宅 腐 基 渣 四 极 品","n":14,"u":"jp"},{"t":"長門有希","n":14,"i":32},{"t":"班固米海龟汤协会","n":13,"i":4561},{"t":"浮泽","n":13,"i":4479},{"t":"番组存档","n":13,"i":4219},{"t":"フリーゲーム","n":13,"i":4194},{"t":"Ar Live网络播客电台","n":13,"i":3808},{"t":"我爱冈田妈妈","n":13,"i":1690},{"t":"【招募】世界超无趣人类退化委员会","n":13,"i":1657},{"t":"FREE！男子游泳部","n":13,"i":1630},{"t":"二次元の世界","n":13,"i":1574},{"t":"隐晦茶话会","n":13,"u":"lament"},{"t":"靈異陰陽錄","n":13,"i":1501},{"t":"中二病也要谈恋爱","n":13,"i":1433},{"t":"我们都爱D娘","n":13,"i":1281},{"t":"天鳳研究协会","n":13,"i":1220},{"t":"目测党","n":13,"i":1214},{"t":"三无少女研究小组","n":13,"i":1205},{"t":"吐槽网","n":13,"i":1157},{"t":"【紅魔館】","n":13,"i":900},{"t":"耽美cp","n":13,"i":860},{"t":"朴璐美","n":13,"i":858},{"t":"埃及","n":13,"i":704},{"t":"ALL27同萌会","n":13,"u":"all27"},{"t":"云雀恭弥","n":13,"i":573},{"t":"Selfy Town (Tinierme)","n":13,"i":516},{"t":"HSM","n":13,"i":482},{"t":"鳥海浩輔","n":13,"i":450},{"t":"合肥市二元论哲学体系研究讨论小组","n":13,"i":330},{"t":"MeltyBlood月姬格鬥","n":13,"i":326},{"t":"MAD研究會","n":13,"i":255},{"t":"LOLI同好会","n":13,"u":"loli"},{"t":"古屋兎丸","n":13,"i":99},{"t":"聖条学園“連合軍第501統合戦闘航空団”小褲褲研究會 奸 PPG輕小說裙菊花 基 M燈寢猥隊財務部","n":13,"i":38},{"t":"无敌世纪少年","n":13,"i":9},{"t":"感情夜话","n":12,"u":"love"},{"t":"Alicesoft","n":12,"i":4278},{"t":"Bangumi番组计划 for iOS","n":12,"u":"bgm_ios"},{"t":"種田梨沙","n":12,"i":4023},{"t":"二次元领域","n":12,"i":3993},{"t":"－","n":12,"u":"nj454"},{"t":"番組黃油","n":12,"i":3799},{"t":"数码产品的那些破烂事~~~","n":12,"i":1692},{"t":"木村良平","n":12,"i":1677},{"t":"青黄","n":12,"i":1618},{"t":"催头像狂魔同好会","n":12,"i":1605},{"t":"蜜桃社","n":12,"i":1560},{"t":"盾铁一生推痴汉集中营","n":12,"i":1528},{"t":"绘漫社","n":12,"i":1203},{"t":"银他妈！看你所不知道、想知道的事情","n":12,"i":915},{"t":"早见沙织","n":12,"i":914},{"t":"Jジジと愉快な仲間たち","n":12,"i":899},{"t":"愉快的大學生活","n":12,"i":773},{"t":"落差萌","n":12,"i":697},{"t":"E-HA 发热工房","n":12,"u":"eha"},{"t":"禁组","n":12,"i":616},{"t":"鸭梨拍卖协会","n":12,"i":553},{"t":"cosplay交流小组","n":12,"i":480},{"t":"HCG交流委员会","n":12,"i":384},{"t":"日剧小组","n":12,"i":358},{"t":"安达控","n":12,"i":337},{"t":"科幻世界","n":12,"u":"sfw"},{"t":"野中藍","n":12,"i":175},{"t":"佐倉紗織","n":12,"i":166},{"t":"COMIC RIN","n":12,"i":157},{"t":"菅野ひろゆき（剣乃ゆきひろ）","n":12,"i":148},{"t":"鬼頭莫宏","n":12,"i":141},{"t":"就爱看热闹","n":12,"i":22},{"t":"菠萝子的朝觐地","n":12,"i":15},{"t":"白色相簿同好会","n":11,"i":4348},{"t":"育儿","n":11,"i":4033},{"t":"父嫁添足同好会肇庆分会","n":11,"i":3983},{"t":"镇江ACG同好会","n":11,"i":3756},{"t":"B娘的午后甜点树莓派","n":11,"i":1688},{"t":"Microsoft Visual Studio","n":11,"i":1686},{"t":"秦时明月","n":11,"i":1573},{"t":"MAD练习室","n":11,"i":1523},{"t":"吃货","n":11,"i":1499},{"t":"刀剑神域同好会","n":11,"i":1465},{"t":"菜鸟CG研究大会= =","n":11,"i":1456},{"t":"VOCALOIDCHINA","n":11,"i":1455},{"t":"口袋妖怪","n":11,"i":1437},{"t":"情報屋","n":11,"i":1300},{"t":"eMule","n":11,"i":1286},{"t":"新人报道组","n":11,"i":1221},{"t":"read, or DIE!!!","n":11,"i":1181},{"t":"小仓唯","n":11,"i":1019},{"t":"腐化地带周边工作室","n":11,"i":951},{"t":"Treow同好共享圈","n":11,"i":861},{"t":"电饭煲党&简单烹饪","n":11,"i":837},{"t":"高画质在线动画资源","n":11,"i":810},{"t":"彭格列公关部","n":11,"i":764},{"t":"A凸组","n":11,"i":730},{"t":"岸田梅爾","n":11,"i":710},{"t":"杉山紀彰","n":11,"i":698},{"t":"不良渣子組","n":11,"i":655},{"t":"中国动画~Chinanimation","n":11,"i":611},{"t":"文藝部","n":11,"i":582},{"t":"+骸云+","n":11,"i":575},{"t":"二次元伪娘基佬收留的地方丶","n":11,"i":559},{"t":"惠州二次元应援会","n":11,"i":524},{"t":"夏彻","n":11,"i":512},{"t":"Stack Overflow","n":11,"i":505},{"t":"桑島法子","n":11,"i":401},{"t":"古都西安搅基养成机密结社","n":11,"i":368},{"t":"加拿大同好会","n":11,"i":357},{"t":"真希波FANS聚集地","n":11,"i":354},{"t":"我是一只瘦弱的攻","n":11,"i":307},{"t":"学园的gal，gal的学园","n":11,"u":"school_gal"},{"t":"大槍葦人","n":11,"i":176},{"t":"propeller","n":11,"i":102},{"t":"可利用厕纸","n":10,"i":4526},{"t":"神山高校古典部","n":10,"i":4490},{"t":"bgm记梦小组","n":10,"i":4396},{"t":"富野佬吹水小组","n":10,"i":4390},{"t":"极恶非道晚睡派","n":10,"i":4295},{"t":"天城Pro","n":10,"i":4154},{"t":"air黑吧","n":10,"i":4147},{"t":"翻译小组","n":10,"i":4070},{"t":"kindle","n":10,"i":4066},{"t":"插画控の天堂","n":10,"i":4046},{"t":"PSN℠","n":10,"i":3992},{"t":"德井青空","n":10,"i":3982},{"t":"关智一","n":10,"i":3939},{"t":"今晚吃什么","n":10,"i":3898},{"t":"东山奈央","n":10,"i":3877},{"t":"日升厨","n":10,"i":3819},{"t":"自来熟の逗比","n":10,"i":3803},{"t":"神龙组","n":10,"i":1681},{"t":"魔都突击展会组","n":10,"i":1679},{"t":"优动漫","n":10,"i":1678},{"t":"前进的心心and大家","n":10,"i":1604},{"t":"洛天依资源交流会","n":10,"i":1549},{"t":"我又忘了要看什么了","n":10,"i":1408},{"t":"YES!RPG!-牛郎店殺馬特-","n":10,"i":1328},{"t":"动物之森","n":10,"i":1305},{"t":"小透明也爱ACG","n":10,"i":1242},{"t":"内田真礼","n":10,"i":1222},{"t":"古典部","n":10,"u":"classical"},{"t":"深圳二次元","n":10,"i":1143},{"t":"萌正太.萌少年","n":10,"i":1011},{"t":"タオルケットをもう一度","n":10,"i":974},{"t":"月時計","n":10,"i":972},{"t":"我们是糟糕的撞头小队","n":10,"i":934},{"t":"ボーカロイドの歌詞置場","n":10,"i":847},{"t":"JUBEAT同好会","n":10,"i":833},{"t":"法语","n":10,"i":813},{"t":"【异次元卖萌同好会☆~】","n":10,"i":791},{"t":"逆轉裁判-成御","n":10,"i":776},{"t":"BGM武汉战略总部","n":10,"u":"wuhan"},{"t":"菟缌子家孩子的集结地=V=","n":10,"i":742},{"t":"K-ON梓喵同樂會!!","n":10,"i":727},{"t":"不合群小组","n":10,"i":692},{"t":"黑礁","n":10,"i":658},{"t":"みーちゃん","n":10,"i":615},{"t":"游戏开发","n":10,"i":532},{"t":"浪費生命系列","n":10,"u":"wasteoflife"},{"t":"Chobits","n":10,"i":389},{"t":"SOSG漫画组","n":10,"i":346},{"t":"NEET侦探社","n":10,"i":320},{"t":"亚细亚NO.1","n":10,"i":318},{"t":"他喵的,我要吐槽！","n":10,"i":305},{"t":"RayFile资源","n":10,"i":266},{"t":"Youtube","n":10,"u":"youtube"},{"t":"水橋かおり","n":10,"i":227},{"t":"冲方丁","n":10,"i":144},{"t":"越界内容","n":10,"i":26},{"t":"hufi","n":9,"i":4567},{"t":"熬夜型猝死调查会","n":9,"i":4431},{"t":"姐控","n":9,"i":4355},{"t":"星漫奖比赛现场集锦","n":9,"i":4323},{"t":"TRPG","n":9,"i":4310},{"t":"云村动画讨论小组","n":9,"i":4218},{"t":"BL游戏的心水聚集地","n":9,"i":4167},{"t":"书房","n":9,"i":4158},{"t":"成年人的ACG世界","n":9,"i":4142},{"t":"战舰少女R虫群会议室","n":9,"i":4129},{"t":"幻想自己是文豪","n":9,"i":4050},{"t":"あの夏~our summer story~","n":9,"i":3977},{"t":"挑刺儿","n":9,"i":3972},{"t":"何以笙箫默","n":9,"i":3971},{"t":"跪求动画化！！","n":9,"u":"animeka"},{"t":"荣耀爱残联盟","n":9,"i":3862},{"t":"新井里美","n":9,"i":3780},{"t":"-绯然久夏-题绘社","n":9,"i":1725},{"t":"wp8","n":9,"i":1598},{"t":"言和","n":9,"i":1579},{"t":"丧尸","n":9,"i":1577},{"t":"反射弧特长","n":9,"i":1570},{"t":"Webcomic","n":9,"i":1491},{"t":"番组Wiki调教屋","n":9,"i":1470},{"t":"深井冰社团","n":9,"i":1389},{"t":"MAD","n":9,"i":1280},{"t":"可排泄的生化实验大全","n":9,"i":1246},{"t":"浙江ACG同会","n":9,"i":1170},{"t":"幻想乡","n":9,"i":959},{"t":"神圣布里塔尼亚帝国黑色搅基团","n":9,"i":949},{"t":"android学习与开发","n":9,"u":"androidmaster"},{"t":"广州ACG同人交流会","n":9,"i":904},{"t":"SOS团","n":9,"i":846},{"t":"萌=99%可爱+1%工口","n":9,"i":753},{"t":"幻想乡","n":9,"i":745},{"t":"宅魂腐道","n":9,"i":717},{"t":"高橋広樹","n":9,"i":699},{"t":"PlayStation2™","n":9,"i":667},{"t":"Hero姐应援会","n":9,"i":474},{"t":"萝卜之魂","n":9,"i":341},{"t":"_","n":9,"i":308},{"t":"MiddleIsland","n":9,"i":248},{"t":"ZIZZ STUDIO","n":9,"i":161},{"t":"小梅けいと","n":9,"i":155},{"t":"MOSAIC.WAV","n":9,"i":150},{"t":"栗林みな実","n":9,"i":149},{"t":"機動戦艦ナデシコ","n":9,"i":142},{"t":"甘詰留太","n":9,"i":108},{"t":"将“萌”彻底公式化低俗化商业化的研讨会","n":9,"i":97},{"t":"埃米尔物语","n":9,"i":70},{"t":"我就是我就有","n":8,"i":4321},{"t":"黑暗之魂系列","n":8,"i":4282},{"t":"Dota 2","n":8,"i":4244},{"t":"兰斯系列","n":8,"i":4148},{"t":"日常部","n":8,"i":4127},{"t":"Drama爱好者","n":8,"i":4107},{"t":"Art, freedom and beauty","n":8,"i":4098},{"t":"老年人","n":8,"i":4083},{"t":"三八子 / Mihako","n":8,"i":4049},{"t":"/group/coding","n":8,"u":"coding"},{"t":"⚾️棒球","n":8,"i":4012},{"t":"御坂网络","n":8,"i":3991},{"t":"双马尾","n":8,"i":3974},{"t":"----------------","n":8,"i":3964},{"t":"秘封少女俱乐部","n":8,"u":"sealed"},{"t":"IFTTT","n":8,"i":3902},{"t":"青岛MAGN同好会","n":8,"u":"qingdao"},{"t":"晓江╭(╯3╰)╮初花","n":8,"i":3741},{"t":"脑洞全开的暴走少年们","n":8,"i":1632},{"t":"我不受欢迎怎么想都是你们的错ヽ(#`Д´)ﾉ","n":8,"i":1602},{"t":"日语学习软件分享，测试与招募","n":8,"i":1587},{"t":"不明","n":8,"i":1582},{"t":"魔都！","n":8,"u":"modu"},{"t":"超级无敌霹雳手绘大师","n":8,"i":1472},{"t":"广州萤火虫动漫嘉年华,fiying。","n":8,"i":1464},{"t":"青少年心理健康","n":8,"i":1452},{"t":"乙女","n":8,"i":1406},{"t":"百度天窗联盟吧","n":8,"i":1382},{"t":"系色企鹅","n":8,"i":1339},{"t":"リョナ","n":8,"i":1301},{"t":"Bangumi Sora","n":8,"i":1290},{"t":"午茶社管理部","n":8,"i":1288},{"t":"美少女游戏生肉鉴赏组","n":8,"u":"galzuki"},{"t":"暗黑破坏神3","n":8,"i":1144},{"t":"天香字幕社","n":8,"i":1035},{"t":"東亜重工","n":8,"i":979},{"t":"洋装娘的基地！","n":8,"u":"lolita"},{"t":"天朝ACG跨省应援议会","n":8,"i":859},{"t":"德語","n":8,"i":835},{"t":"BGM武大战略局","n":8,"u":"whu"},{"t":"加藤英美里","n":8,"i":746},{"t":"搵兩餐","n":8,"i":714},{"t":"細谷佳正","n":8,"i":700},{"t":"DASOKU","n":8,"i":669},{"t":"J-Rock狂热","n":8,"i":654},{"t":"欧米音乐","n":8,"i":603},{"t":"GOD EATER 極東支部","n":8,"i":591},{"t":"佐藤聡美","n":8,"i":499},{"t":"新番音樂 同人音樂ww","n":8,"i":484},{"t":"噗浪","n":8,"i":468},{"t":"iPad","n":8,"i":424},{"t":"巫女应援会","n":8,"i":413},{"t":"奥里加纪念医院","n":8,"i":350},{"t":"拇指派别","n":8,"i":334},{"t":"OGC～技术的确是可怕滴～","n":8,"i":303},{"t":"電気式華憐音楽集団","n":8,"i":162},{"t":"鬼束直","n":8,"i":158},{"t":"最萌トナメ","n":8,"i":119},{"t":"癒月","n":8,"i":117},{"t":"Phantom -PHANTOM OF INFERNO-","n":8,"i":110},{"t":"汉化小组哦哦哦","n":8,"i":90},{"t":"兰卡·李","n":8,"i":17},{"t":"个人资源放流","n":7,"i":4571},{"t":"北宇治动画交流","n":7,"u":"kumiko"},{"t":"桌游小组","n":7,"u":"zhuoyou"},{"t":"STEAM挖宝小组","n":7,"i":4522},{"t":"夏日相扑大会","n":7,"i":4504},{"t":"每天都看番才是正确人生","n":7,"u":"keaiyun1028"},{"t":"同人RPG游戏番组计划","n":7,"u":"rpggames"},{"t":"新番讨论组","n":7,"i":4410},{"t":"养老院","n":7,"i":4394},{"t":"PROJECTOR|幻象孵化机","n":7,"i":4380},{"t":"食玩测评小组","n":7,"i":4373},{"t":"vtuber自由讨论","n":7,"u":"vtuber"},{"t":"掌中咲良田伊甸","n":7,"i":4238},{"t":"搭一个弹幕视频站","n":7,"u":"bgmi"},{"t":"银河最大ACGN交流小组","n":7,"i":4212},{"t":"上海galgame","n":7,"i":4188},{"t":"枕","n":7,"i":4156},{"t":"SCAP动漫社","n":7,"i":4138},{"t":"WANI社今天倒闭了吗","n":7,"u":"antiwani"},{"t":"同人创作小组","n":7,"u":"tujilovelinmao"},{"t":"sgamer","n":7,"i":4068},{"t":"音声鉴赏会","n":7,"i":4042},{"t":"腐向漫画研究组","n":7,"u":"blmanga"},{"t":"大连Bangumi同好会","n":7,"i":3998},{"t":"-","n":7,"i":3994},{"t":"长春华山","n":7,"i":3989},{"t":"日剧博爱党求参本","n":7,"u":"dorama"},{"t":"arclive","n":7,"i":3968},{"t":"云骸","n":7,"i":3900},{"t":"高达","n":7,"i":3832},{"t":"北辰高中二年一班委员会","n":7,"i":3805},{"t":"乐器演奏","n":7,"i":3794},{"t":"丧心病狂","n":7,"i":1726},{"t":"魔都腐货组","n":7,"i":1682},{"t":"没人","n":7,"i":1580},{"t":"二次元","n":7,"i":1556},{"t":"笨蛋聚集地","n":7,"i":1520},{"t":"K","n":7,"i":1505},{"t":"博丽节操社","n":7,"i":1488},{"t":"六次元","n":7,"i":1416},{"t":"k-on輕音部(討論區)","n":7,"u":"happy603"},{"t":"游戏实况同好会","n":7,"i":1302},{"t":"nitroplus","n":7,"i":1260},{"t":"君染家應援組","n":7,"i":1243},{"t":"HunterXHunter的抖M聚集地","n":7,"i":1200},{"t":"美影厂NC粉聚集地","n":7,"i":1183},{"t":"不丢东西会死星","n":7,"u":"lostthings"},{"t":"冻鳗研究烩","n":7,"i":1148},{"t":"和泉つばす","n":7,"i":1009},{"t":"纯涩堂","n":7,"i":991},{"t":"纹清桐野鉴","n":7,"i":977},{"t":"蝦米looper","n":7,"i":973},{"t":"Heru3的集中地","n":7,"i":932},{"t":"Mac互助会","n":7,"i":879},{"t":"盐泽兼人","n":7,"i":831},{"t":"枫叶国GTA地区基友团","n":7,"i":825},{"t":"半死不活村","n":7,"i":801},{"t":"二次元纯爱组","n":7,"i":779},{"t":"原漫BUS","n":7,"i":772},{"t":"監督","n":7,"i":734},{"t":"魂淡字幕组","n":7,"i":709},{"t":"上海吃货组","n":7,"i":693},{"t":"灵夏柒度","n":7,"u":"lingxiaqidu"},{"t":"宅前腐后","n":7,"i":664},{"t":"赤龟天道","n":7,"i":652},{"t":"五星物语","n":7,"i":585},{"t":"痴汉馆","n":7,"i":578},{"t":"夢日記","n":7,"i":569},{"t":"寺岛拓笃","n":7,"i":561},{"t":"爱斯基猎人集会所","n":7,"i":554},{"t":"蟹爪","n":7,"i":493},{"t":"デュラララ（來良组主）","n":7,"i":463},{"t":"Mitha ♡ ～","n":7,"i":412},{"t":"本命是死跑龙套的同好会","n":7,"i":406},{"t":"第1121小隊","n":7,"i":394},{"t":"魅族 M8 小组","n":7,"i":391},{"t":"好人部落","n":7,"i":367},{"t":"山城不來電樂團","n":7,"i":365},{"t":"妹控（要低调","n":7,"u":"mm"},{"t":"我们不要Loli春菜","n":7,"i":179},{"t":"蜜柑屋","n":7,"u":"aoibits"},{"t":"桃井はるこ","n":7,"i":159},{"t":"有葉","n":7,"i":116},{"t":"藍ちゃん","n":7,"i":111},{"t":"古谷実","n":7,"i":109},{"t":"DEMO","n":7,"u":"demo"},{"t":"零","n":7,"u":"fatal_frame"},{"t":"V2EX","n":7,"u":"v2ex"},{"t":"雷普人生茶话会","n":6,"i":4415},{"t":"组件实验室","n":6,"i":4397},{"t":"型月茶会","n":6,"i":4354},{"t":"拉丁语","n":6,"i":4341},{"t":"Moe Sugar","n":6,"i":4322},{"t":"世界語 Esperanto","n":6,"i":4291},{"t":"恋音主机丶","n":6,"u":"onec"},{"t":"什么都能问","n":6,"u":"ama"},{"t":"烂片分锅委员会","n":6,"u":"bad"},{"t":"白咲学院","n":6,"i":4183},{"t":"漫画感想","n":6,"i":4177},{"t":"Galgame相关","n":6,"i":4170},{"t":"二次风电音","n":6,"i":4140},{"t":"声豚","n":6,"i":4123},{"t":"studiotuhai","n":6,"i":4115},{"t":"艺术狂热者の杂谈俱乐部","n":6,"i":4056},{"t":"steam喜加1","n":6,"i":4021},{"t":"白箱shirobako","n":6,"i":4013},{"t":"TFBOYS","n":6,"i":4008},{"t":"吃","n":6,"i":4004},{"t":"二次元讨论","n":6,"i":4000},{"t":"神州萌兽祭 兽人相关讨论组","n":6,"i":3995},{"t":"枪神纪","n":6,"i":3966},{"t":"日笠阳子","n":6,"i":3893},{"t":"煎饼社","n":6,"i":3866},{"t":"小見川千明","n":6,"u":"chiaki"},{"t":"电子神技大学动画爱好者","n":6,"i":3771},{"t":"游戏设计","n":6,"i":3765},{"t":"小日家求参本QWQ","n":6,"i":1689},{"t":"今天的我也很高兴","n":6,"i":1627},{"t":"＞＜","n":6,"i":1624},{"t":"摊主周边拼单大集合！","n":6,"i":1622},{"t":"天朝各地展会摊主、游客，拼房和宿集中站","n":6,"i":1617},{"t":"养耳的音乐","n":6,"i":1615},{"t":"Vancouver","n":6,"i":1600},{"t":"非典型动漫","n":6,"i":1557},{"t":"喵鱼","n":6,"i":1544},{"t":"絵空事","n":6,"i":1514},{"t":"摇滚乐爱好者","n":6,"i":1458},{"t":"ACG指弹","n":6,"i":1434},{"t":"素晴らしい電波観測所","n":6,"i":1421},{"t":"地球OL","n":6,"u":"earth_online"},{"t":"Sacred Younger Sisters Union","n":6,"i":1336},{"t":"字体控","n":6,"i":1327},{"t":"-","n":6,"i":1323},{"t":"特撮研究会","n":6,"i":1282},{"t":"晚","n":6,"i":1262},{"t":"Gumi Fansite","n":6,"i":1248},{"t":"这是一个非公开的小组0。 0","n":6,"i":1158},{"t":"Evernote","n":6,"i":1154},{"t":"妖狐X仆SS","n":6,"u":"yaohuxpuss"},{"t":"zero苦逼厨","n":6,"i":1117},{"t":"HKG字幕組","n":6,"i":1034},{"t":"荔枝☆光芒俱乐部","n":6,"i":1020},{"t":"膝盖中箭同好会","n":6,"i":1018},{"t":"千歳的小黑屋","n":6,"u":"thec"},{"t":"粤语同萌会","n":6,"i":957},{"t":"杭州腐都","n":6,"i":921},{"t":"麻将爱好者","n":6,"i":888},{"t":"近藤隆こんどう　たかし","n":6,"u":"jtl"},{"t":"卡通总动员","n":6,"i":881},{"t":"独立游戏","n":6,"u":"indiegame"},{"t":"扬州宅","n":6,"i":870},{"t":"天朝七人众","n":6,"i":865},{"t":"动漫模型讨论","n":6,"i":829},{"t":"BGM华科战略部","n":6,"u":"hust"},{"t":"魔都同城联谊会","n":6,"i":755},{"t":"nero('ω`)ふぁんこみゅ♪","n":6,"i":754},{"t":"口袋秘密基地","n":6,"i":648},{"t":"我们都是蹭的累","n":6,"i":631},{"t":"冲田总司【新撰组异闻录】","n":6,"i":624},{"t":"blackberry黨","n":6,"i":571},{"t":"少年偵探團","n":6,"i":503},{"t":"starry-sky(spring to winter)","n":6,"i":475},{"t":"马克OS","n":6,"i":466},{"t":"bangumi京黑中心","n":6,"i":441},{"t":"DA同音愛漫","n":6,"i":392},{"t":"LeftField冷锋团","n":6,"i":388},{"t":"无限之住人","n":6,"i":376},{"t":"恶搞是王道","n":6,"i":347},{"t":"天之妃女学园","n":6,"i":327},{"t":"Music","n":6,"u":"music"},{"t":"傲娇吧！","n":6,"u":"aojiao"},{"t":"团长*大家族","n":6,"i":277},{"t":"BitTorrent","n":6,"i":240},{"t":"Lost Moe!","n":6,"i":215},{"t":"LVHime的秘密花园","n":6,"i":212},{"t":"PIVIX","n":6,"i":194},{"t":"鬼ノ仁","n":6,"i":170},{"t":"遊女","n":6,"i":164},{"t":"JOJO","n":6,"u":"jojo"},{"t":"倉田佐祐理","n":6,"i":125},{"t":"麻帆良战队HentaiRanger","n":6,"i":33},{"t":"黄金十二宫-牧羊","n":6,"i":18},{"t":"摇曳の露营","n":5,"i":4520},{"t":"运动打卡","n":5,"i":4474},{"t":"Bangumi 神奇自然现象观察","n":5,"i":4472},{"t":"My home","n":5,"i":4401},{"t":"江西人在哪里～(￣▽￣～)~","n":5,"i":4344},{"t":"看看听听","n":5,"u":"kktt"},{"t":"大神看看我头像什么番","n":5,"i":4300},{"t":"准备转型中……","n":5,"i":4284},{"t":"能不能厚个脸皮求一下那种本子的作者可以的话谢谢了","n":5,"u":"a8231"},{"t":"网文爱好者","n":5,"i":4206},{"t":"廃墟に咲く箱庭","n":5,"i":4193},{"t":"乙女向各种分享地","n":5,"i":4160},{"t":"科研狗","n":5,"i":4153},{"t":"i","n":5,"i":4134},{"t":"新番推荐","n":5,"u":"xftj"},{"t":"最后的深渊","n":5,"i":4097},{"t":"疯狂的我们，疯狂的Rejet","n":5,"i":4081},{"t":"懒人堂","n":5,"i":4063},{"t":"信标","n":5,"i":4001},{"t":"割腿肉的爱斯基摩人","n":5,"u":"lengcp"},{"t":"机动战士高达Seed&Destiny","n":5,"i":3904},{"t":"黑花","n":5,"i":3894},{"t":"设定控","n":5,"i":3879},{"t":"H西奈gal部","n":5,"i":3806},{"t":"水银党","n":5,"i":3789},{"t":"游戏汉化","n":5,"i":3788},{"t":"プリキュア/Precure系列","n":5,"i":3784},{"t":"战地","n":5,"i":3777},{"t":"service同人社","n":5,"i":3742},{"t":"翅膀","n":5,"i":3740},{"t":"自由社团","n":5,"i":1631},{"t":"no life","n":5,"i":1628},{"t":"软件爱好者","n":5,"i":1614},{"t":"像白痴一样-_-","n":5,"i":1607},{"t":"Reddit","n":5,"i":1597},{"t":"叁仟星屑动漫社","n":5,"i":1590},{"t":"集硬社","n":5,"i":1530},{"t":"意呆利梦游仙境","n":5,"u":"wonderland"},{"t":"bjd","n":5,"u":"bjd"},{"t":"iOS与OS X开发","n":5,"u":"idev"},{"t":"鹿角镇","n":5,"i":1478},{"t":"vocaloid同好协会","n":5,"u":"vocaliod"},{"t":"面码领域","n":5,"i":1436},{"t":"北京の腐の道","n":5,"i":1435},{"t":"高达uc","n":5,"i":1431},{"t":"平原反抗组织","n":5,"i":1415},{"t":"school days","n":5,"i":1395},{"t":"「脳浆炸裂小組」","n":5,"i":1333},{"t":"Paradisus","n":5,"u":"paradisus"},{"t":"寻找心爱的萌动漫","n":5,"i":1287},{"t":"苏州好地方●ω●","n":5,"u":"suzhou"},{"t":"PC单机游戏资源","n":5,"i":1240},{"t":"ぐるたみん","n":5,"i":1223},{"t":"浪川大辅","n":5,"i":1191},{"t":"小说次元","n":5,"i":1184},{"t":"Diablo","n":5,"i":1162},{"t":"飞跃GFW","n":5,"i":1147},{"t":"CARNELIAN","n":5,"i":1130},{"t":"抵制国漫，纯日组","n":5,"u":"dizhiguoman"},{"t":"基友","n":5,"u":"jiyou"},{"t":"K岛","n":5,"i":1041},{"t":"兄贵预备班","n":5,"i":1030},{"t":"秀吉","n":5,"i":1012},{"t":"零个共同喜好","n":5,"u":"commonality"},{"t":"四格同好","n":5,"u":"yonkoma"},{"t":"我们都是高三党","n":5,"u":"gaosan"},{"t":"色胆包青天","n":5,"i":960},{"t":"神威がくぽ","n":5,"i":943},{"t":"田村ゆかりX水樹奈々","n":5,"i":941},{"t":"≋ὥ≋飞面神教≋ὥ≋ ‮","n":5,"i":930},{"t":"基友一生一起走","n":5,"u":"jilao"},{"t":"LYCEE","n":5,"u":"lycee"},{"t":".","n":5,"i":889},{"t":"梁春日的忧郁","n":5,"i":885},{"t":"尸口巾","n":5,"i":862},{"t":"想做主催~！","n":5,"u":"boom0413"},{"t":"BC同人动力","n":5,"i":826},{"t":"空","n":5,"i":799},{"t":"冷場","n":5,"u":"cold"},{"t":"塔羅牌協會","n":5,"i":770},{"t":"Wii机动队","n":5,"i":711},{"t":"朽木露琪亚相关资源供给","n":5,"i":705},{"t":"黑猫白猫一起来，五更琉璃","n":5,"i":691},{"t":"增殖吧Shimeji！","n":5,"i":663},{"t":"衕仁ы誌","n":5,"i":636},{"t":"大家來追情景喜劇啊喂","n":5,"i":633},{"t":"iPhone4","n":5,"u":"iphone4"},{"t":"DirectX开发","n":5,"i":545},{"t":"水月陵","n":5,"i":530},{"t":"南宁","n":5,"u":"nn"},{"t":"研究与开发中心","n":5,"i":502},{"t":"四次元","n":5,"i":470},{"t":"卡爾地卡喫茶店地下室","n":5,"i":396},{"t":"駕籠真太郎","n":5,"i":372},{"t":"Fuck My Life","n":5,"u":"fuck"},{"t":"世界扑灭委员会","n":5,"i":239},{"t":"伊藤大人的洞穴=_,=","n":5,"i":189},{"t":"Natural Selection","n":5,"u":"ns"},{"t":"南央美","n":5,"i":153},{"t":"菊池政治","n":5,"i":138},{"t":"川澄舞","n":5,"i":123},{"t":"世界の中心で、愛をさけぶ","n":5,"i":112},{"t":"大槻ケンヂ","n":5,"i":100},{"t":"腐宅","n":5,"i":81},{"t":"ゆの同好会","n":5,"i":29},{"t":"伊起追番","n":4,"i":4547},{"t":"消失的 Bangumi","n":4,"i":4543},{"t":"炎孕爱好小组","n":4,"i":4541},{"t":"阿巴阿巴","n":4,"u":"abaaba"},{"t":"Brokechain Daily","n":4,"i":4527},{"t":"屑的垃圾桶","n":4,"i":4525},{"t":"德国同好会","n":4,"i":4506},{"t":"中国足球","n":4,"i":4501},{"t":"樱丘没有女子高校","n":4,"i":4499},{"t":"现代炼金术","n":4,"i":4485},{"t":"丹迪q群小组","n":4,"i":4475},{"t":"奇奇怪怪的聚集地","n":4,"i":4458},{"t":"开车么？","n":4,"i":4425},{"t":"汽车俱乐部//玩家社区","n":4,"i":4406},{"t":"哲学思辨","n":4,"i":4400},{"t":"魔兽之卵","n":4,"i":4398},{"t":"vtuber（二次元搞笑主播）单推组","n":4,"i":4382},{"t":"有趣的小组","n":4,"i":4366},{"t":"一千零一梦研会","n":4,"i":4339},{"t":"流动冰淇淋车","n":4,"i":4338},{"t":"荣格心理学","n":4,"i":4333},{"t":"光之美少女","n":4,"i":4326},{"t":"我们都爱阅读","n":4,"i":4249},{"t":"为了不成为NEET并立志当上现充而持续奋斗的只有一人的漫画讨论小组","n":4,"i":4216},{"t":"沙盒","n":4,"i":4215},{"t":"Scala 开发者","n":4,"i":4201},{"t":"星之梦","n":4,"u":"xingzhimeng"},{"t":"VS Code","n":4,"i":4169},{"t":"假装看新番","n":4,"i":4165},{"t":"東雲研究所","n":4,"i":4150},{"t":"水岛努同好会","n":4,"i":4120},{"t":"看脸的世界","n":4,"i":4103},{"t":"纳年纳兔纳些事儿","n":4,"i":4096},{"t":"多少","n":4,"u":"dgfdh"},{"t":"印象色","n":4,"i":4067},{"t":"南条爱乃","n":4,"u":"nt"},{"t":"完结综合症","n":4,"i":4060},{"t":"Matt Bomer","n":4,"i":3996},{"t":"萌动漫学社咪咪","n":4,"u":"dongmancv"},{"t":"剑三姨妈念破","n":4,"u":"thlm"},{"t":"Ruby & Rails","n":4,"i":3890},{"t":"koeda同好小组","n":4,"i":3882},{"t":"服务","n":4,"i":3881},{"t":"Ink Meeting 会吐墨","n":4,"u":"inkmeeting"},{"t":"谁接寄售啊！( \"·ω·゛)","n":4,"i":3871},{"t":"琼花文学","n":4,"i":3870},{"t":"潘多拉之心(pH)","n":4,"i":3869},{"t":"冈本信彦","n":4,"i":3830},{"t":"游戏tern_MG","n":4,"i":3826},{"t":"滨州ACG同好会","n":4,"u":"bzacg"},{"t":"窗w","n":4,"i":3796},{"t":"AKB同人本集散地","n":4,"i":3793},{"t":"人类的可能性","n":4,"i":3767},{"t":"猫团","n":4,"i":3761},{"t":"思宅为何","n":4,"i":3754},{"t":"伴孤蜜NIS分会","n":4,"i":1695},{"t":"社團","n":4,"i":1646},{"t":"星罗棋布","n":4,"i":1609},{"t":"lo娘","n":4,"i":1603},{"t":"极黑的布伦希尔特","n":4,"i":1591},{"t":"花草树木","n":4,"i":1585},{"t":"Haibara Ai","n":4,"i":1572},{"t":"天窗湘军搅基会","n":4,"i":1540},{"t":"幽幽子殿下舔足同好会","n":4,"i":1522},{"t":"唠唠小伙伴儿的日常吧","n":4,"i":1512},{"t":"安卓发烧友","n":4,"i":1490},{"t":"抖M集中营(*´∀`)ノ","n":4,"i":1485},{"t":"爱的威尼斯","n":4,"u":"aideweinisi"},{"t":"叁叁壹","n":4,"i":1469},{"t":"upsuper‘s playground","n":4,"u":"upsuper"},{"t":"魔都のcosplay","n":4,"i":1450},{"t":"Intel","n":4,"i":1427},{"t":"节操丢失人生馆","n":4,"i":1425},{"t":"WII U","n":4,"i":1417},{"t":"易經","n":4,"i":1409},{"t":"蝶組","n":4,"i":1375},{"t":"二次元研讨社","n":4,"i":1365},{"t":"原始社会","n":4,"u":"cg"},{"t":"阿爾法大三角","n":4,"i":1330},{"t":"身体和心灵的全部服从是一件美妙的事","n":4,"i":1324},{"t":"妹控leader ★☆","n":4,"i":1277},{"t":"教练，我要造高达","n":4,"u":"zhongqing"},{"t":"Perfume","n":4,"i":1271},{"t":"东方幻想乡DOTS宣传组","n":4,"i":1259},{"t":"新番茶话会☆","n":4,"i":1241},{"t":"野生番组娘","n":4,"i":1236},{"t":"CHESS","n":4,"i":1188},{"t":"星界","n":4,"i":1185},{"t":"闲影居","n":4,"i":1168},{"t":"太阳的宿敌!","n":4,"u":"yami"},{"t":"君之仆同盟","n":4,"u":"junzhiputongmeng"},{"t":"洛丽塔","n":4,"i":1136},{"t":"九九八十一","n":4,"i":1135},{"t":"Individual.Guilt","n":4,"u":"individual"},{"t":"百鬼夜行","n":4,"u":"bgyx"},{"t":"湛岚组","n":4,"i":1109},{"t":"动漫发烧友","n":4,"i":1036},{"t":"深崎暮人","n":4,"i":1000},{"t":"好苦逼组","n":4,"i":992},{"t":"旧金山湾区","n":4,"u":"bayarea"},{"t":"Journeying Story","n":4,"u":"journeyingstory"},{"t":"Magic Laboratory","n":4,"i":970},{"t":"技术宅类","n":4,"i":969},{"t":"中国移动通信","n":4,"u":"chinamobile"},{"t":"五星物语","n":4,"i":945},{"t":"田口宏子","n":4,"u":"taguchi_hiroko"},{"t":"我们都是喵耳控","n":4,"i":828},{"t":"不鬼","n":4,"i":796},{"t":"卡西阿里","n":4,"i":795},{"t":"萝莉萌","n":4,"i":793},{"t":"正太萌","n":4,"i":792},{"t":"淫君的基友联萌！","n":4,"i":790},{"t":"Front End Development","n":4,"i":751},{"t":"志水雪","n":4,"i":740},{"t":"2011.盗墓笔祭","n":4,"i":736},{"t":"市濑秀和","n":4,"i":708},{"t":"现代音声文化研究会","n":4,"i":674},{"t":"重视研","n":4,"i":666},{"t":"羽多野渉❤","n":4,"i":665},{"t":"神奇宝贝同好会","n":4,"i":642},{"t":"伊藤静","n":4,"u":"qwertyuiop"},{"t":"青铜门","n":4,"i":618},{"t":"Neo-Geo NGO","n":4,"i":594},{"t":"Anitan","n":4,"i":556},{"t":"我的妹子不可能那么软","n":4,"i":476},{"t":"人民公厕","n":4,"i":449},{"t":"黑化的小墙角","n":4,"i":439},{"t":"Duca","n":4,"i":414},{"t":"Galden","n":4,"u":"galden"},{"t":"集团","n":4,"i":387},{"t":"前野智昭","n":4,"i":386},{"t":"CG交流","n":4,"i":363},{"t":"天幻死宅俱乐部","n":4,"i":352},{"t":"酱油党","n":4,"i":351},{"t":"リツカ★FC","n":4,"i":329},{"t":"C76","n":4,"u":"comicmarket"},{"t":"S&M","n":4,"u":"sm"},{"t":"Av是个黄金域名","n":4,"u":"av"},{"t":"非mkv我连看都懒的看","n":4,"u":"mkv"},{"t":"动漫资讯","n":4,"i":268},{"t":"春菜fan","n":4,"i":265},{"t":"轻轻搞起沉睡的基情","n":4,"i":252},{"t":"Anti-Thunder","n":4,"i":241},{"t":"SCUBT @nime Group","n":4,"i":232},{"t":"腐魂","n":4,"i":190},{"t":"小黑屋","n":4,"u":"cielo"},{"t":"植芝理一","n":4,"i":169},{"t":"Rahxephon","n":4,"i":152},{"t":"伊吹風子","n":4,"i":124},{"t":"棗鈴","n":4,"i":122},{"t":"八雲剣豪","n":4,"i":115},{"t":"甲子園","n":4,"i":83},{"t":"眼镜娘支援会","n":4,"i":77},{"t":"推到LOLI協會","n":4,"i":71},{"t":"一般小説","n":4,"i":50},{"t":"CPC","n":4,"i":44},{"t":"囧3Pしょ","n":4,"i":41},{"t":"鸡鸡很","n":4,"i":31},{"t":"最萌天顶星人跌卡露加库兰大尉","n":4,"i":20},{"t":"让我们来康点好康的","n":3,"u":"xiagg"},{"t":"艰难找工作","n":3,"i":4535},{"t":"天文观测","n":3,"i":4530},{"t":"新世纪共享战士","n":3,"i":4519},{"t":"Project Anni","n":3,"i":4513},{"t":"SOCC","n":3,"i":4509},{"t":"皇马球迷bgm支部","n":3,"i":4502},{"t":"中央教条区","n":3,"u":"kamiyamakoukou"},{"t":"over 35 OVER","n":3,"i":4487},{"t":"物述提高班","n":3,"i":4478},{"t":"安阳（河南）ACG同好会","n":3,"u":"anyangacg"},{"t":"交通宅吹水会","n":3,"i":4450},{"t":"bangumi体制内工作者闲聊茶话会","n":3,"i":4445},{"t":"为美好世界献上Explosion！","n":3,"u":"megumi"},{"t":"Remake记录簿","n":3,"i":4419},{"t":"注销","n":3,"i":4417},{"t":"小语种杂谈","n":3,"i":4405},{"t":"Liar-Soft社蒸汽朋克系列交流小组","n":3,"i":4393},{"t":"GAINAX","n":3,"i":4383},{"t":"映梦岛——我们的内心独白","n":3,"i":4381},{"t":"打块","n":3,"i":4365},{"t":"电报","n":3,"i":4351},{"t":"特特子的2.5次元空间","n":3,"i":4336},{"t":"同人讨论组","n":3,"i":4318},{"t":"￿","n":3,"u":"lowbee"},{"t":"只推生肉","n":3,"i":4303},{"t":"唐田えりか","n":3,"i":4299},{"t":"幻想乡灌水","n":3,"i":4288},{"t":"关于肥宅艰难求生而迫不得已的日常杂学","n":3,"i":4279},{"t":"平成动画","n":3,"u":"hs_anime"},{"t":"白云山高 珠江水长 广州galgame茶会","n":3,"i":4253},{"t":"哈立德树人的树洞","n":3,"i":4252},{"t":"冬马和纱","n":3,"i":4242},{"t":"解剖","n":3,"u":"money"},{"t":"FL","n":3,"i":4230},{"t":"Anitama","n":3,"i":4214},{"t":"脱宅用空间","n":3,"i":4190},{"t":"bangumi 恋爱计划","n":3,"i":4187},{"t":"中（龄）二（十多岁）少年聚集地","n":3,"i":4182},{"t":"业余冒险解谜开发","n":3,"i":4178},{"t":"黑暗系","n":3,"i":4173},{"t":"网络技术","n":3,"u":"zzyyl"},{"t":"サイボーグ009","n":3,"i":4157},{"t":"林卵","n":3,"i":4149},{"t":"My Works！","n":3,"i":4144},{"t":"吸猫组","n":3,"u":"cccat"},{"t":"女装子交流会","n":3,"i":4135},{"t":"破碎星光","n":3,"i":4128},{"t":"补番小分队","n":3,"i":4113},{"t":"洛杉矶/南加州 分队","n":3,"i":4110},{"t":"弹幕吐槽","n":3,"i":4106},{"t":"钛白金星","n":3,"i":4105},{"t":"地狱型人间动物园","n":3,"i":4094},{"t":"孤独的哲思之旅","n":3,"i":4092},{"t":"灵异段子收录前身单眼同好","n":3,"i":4089},{"t":"音乐tag整理强迫症","n":3,"i":4088},{"t":"you木有","n":3,"u":"ass_56"},{"t":"看我把它改成其他的东东","n":3,"i":4059},{"t":"KARAFURU!","n":3,"i":4052},{"t":"后摇呜噜汪","n":3,"i":4041},{"t":"Chromium","n":3,"i":4031},{"t":"萌豚萌豚萌","n":3,"i":4025},{"t":"昆仑之西","n":3,"i":4016},{"t":"未来学習研究所","n":3,"u":"futurelearninglaboratory"},{"t":"kenn","n":3,"i":3997},{"t":"-","n":3,"i":3878},{"t":"洲崎西","n":3,"i":3874},{"t":"漫画","n":3,"u":"manhua"},{"t":"柯南","n":3,"i":3833},{"t":"弹丸论破","n":3,"i":3824},{"t":"坦克世界","n":3,"i":3809},{"t":"唱见厨集散地☆","n":3,"i":3787},{"t":"深圳动漫节----同人位","n":3,"i":3774},{"t":"黄昏の圣痕","n":3,"i":3773},{"t":"剧场版","n":3,"i":3769},{"t":"闲散类同人作品集散","n":3,"i":3762},{"t":"极限回映","n":3,"i":3746},{"t":"马卡龙真爱委员会","n":3,"u":"xiaodai"},{"t":"杉田桑の痴汉团","n":3,"u":"sugita_chihan"},{"t":"机油们的聚餐会","n":3,"u":"jiyoumendejucanhui"},{"t":"Buriki肉老师w","n":3,"i":1633},{"t":"晚了","n":3,"i":1616},{"t":"东方风铃香","n":3,"i":1608},{"t":"Javascript","n":3,"i":1599},{"t":"Code Geass系列讨论组","n":3,"i":1595},{"t":"所以说内蒙人都不宅么","n":3,"i":1593},{"t":"CG同人交流","n":3,"i":1589},{"t":"绘时代","n":3,"u":"hsd"},{"t":"-","n":3,"u":"x182"},{"t":"MADer 讨论组","n":3,"i":1578},{"t":"自动高潮","n":3,"i":1576},{"t":"网球王子","n":3,"i":1575},{"t":"反射弧特长","n":3,"u":"slowwwwww"},{"t":"围棋足球研究会","n":3,"i":1567},{"t":"黑白風茶會館","n":3,"i":1564},{"t":"NNI同好会","n":3,"i":1558},{"t":"电离子","n":3,"u":"z2333"},{"t":"透明工厂 Dilatory Factory","n":3,"u":"dilatoryfactory"},{"t":"滑子菇高产栽培技术","n":3,"i":1545},{"t":"穹妹~","n":3,"u":"onijia"},{"t":"KASA","n":3,"i":1517},{"t":"尸鬼","n":3,"u":"shiguei10"},{"t":"CREDIT-DECEIVE","n":3,"i":1511},{"t":"魔都TOUHOU ONLY05组委会","n":3,"i":1510},{"t":"Megpoid GUMI","n":3,"i":1507},{"t":"番茄酱","n":3,"i":1498},{"t":"饼玉","n":3,"u":"diunaxing"},{"t":"格子社","n":3,"i":1482},{"t":"All Hail Enako","n":3,"i":1468},{"t":"目录","n":3,"i":1466},{"t":"济南手办同好会","n":3,"u":"jnactoy"},{"t":"我就是这么随便建一个群而已","n":3,"i":1454},{"t":"证务","n":3,"u":"fdghdfhdfh"},{"t":"人民公厕","n":3,"i":1445},{"t":"2222222222","n":3,"i":1442},{"t":"荒野求生","n":3,"u":"meishitianxia"},{"t":"囧的呼唤","n":3,"u":"jiongdehuhuan"},{"t":"动物之森","n":3,"i":1414},{"t":"动作游戏是本命","n":3,"i":1392},{"t":"...","n":3,"i":1374},{"t":"乌诺酒馆","n":3,"u":"uno"},{"t":"地下城与勇士","n":3,"u":"mmmm"},{"t":"北京同好会","n":3,"u":"hgbjgj"},{"t":"手办制作","n":3,"i":1359},{"t":"2b小分队","n":3,"i":1358},{"t":"日漫台词配音党","n":3,"i":1331},{"t":"我爱mole","n":3,"i":1329},{"t":"先生，需要来一点好茶吗","n":3,"i":1314},{"t":"行方不明","n":3,"i":1308},{"t":"高杉晋助的增高鞋墊-`д´-","n":3,"i":1307},{"t":"ACG同好会","n":3,"i":1303},{"t":"荆棘❤黑蔷薇庭院","n":3,"i":1266},{"t":"本格推理派同人會","n":3,"u":"yaoimystery"},{"t":"东方符文祭献","n":3,"i":1250},{"t":"成都搅基小组","n":3,"i":1239},{"t":"播种船希德尼娅","n":3,"i":1234},{"t":"幻想゛二次元だ","n":3,"i":1226},{"t":"flash","n":3,"i":1206},{"t":"Omertà～沉默的法则～","n":3,"i":1204},{"t":"莫慌，抱紧我","n":3,"i":1201},{"t":"通假病毒","n":3,"u":"virus"},{"t":"一桌人","n":3,"i":1182},{"t":"渚薰","n":3,"i":1178},{"t":"绝世90後","n":3,"u":"xjzx90"},{"t":"T2 Anime","n":3,"i":1139},{"t":"哲學","n":3,"i":1111},{"t":"少女病中毒ing","n":3,"i":1002},{"t":"少女心大作戰。","n":3,"i":987},{"t":"澍狸のACG","n":3,"i":985},{"t":"雏见泽症候群","n":3,"i":910},{"t":"四次元dim sum","n":3,"i":906},{"t":"江苏大学 acg同好","n":3,"i":896},{"t":"动漫游戏の触手","n":3,"u":"stmr"},{"t":"次元最强","n":3,"i":892},{"t":"二缺组","n":3,"i":882},{"t":"Anti-Parents","n":3,"i":878},{"t":"NER-V工作室","n":3,"i":873},{"t":"手贱点进去了啊啊啊","n":3,"u":"clickhappy"},{"t":"GATE7","n":3,"i":839},{"t":"宅舞人员集结！","n":3,"i":794},{"t":"dollfiedream","n":3,"i":778},{"t":"Weiβ Schwarz","n":3,"u":"ws"},{"t":"黑手联盟","n":3,"i":738},{"t":"BGM","n":3,"u":"bgm"},{"t":"钢兵特种小分队","n":3,"i":726},{"t":"峰仓和也","n":3,"i":688},{"t":"三渣组","n":3,"i":685},{"t":"五話寺後援會","n":3,"u":"gowadera"},{"t":"我也不知道想要那样！","n":3,"i":643},{"t":"G叁峰会","n":3,"u":"g_three"},{"t":"鬼头莫宏","n":3,"i":579},{"t":"3Q","n":3,"i":552},{"t":"好人帮","n":3,"u":"con"},{"t":"Bo-Blog","n":3,"i":521},{"t":"Tap建站","n":3,"u":"tap"},{"t":"吐槽团","n":3,"i":494},{"t":"めーさく","n":3,"i":490},{"t":"幸福花园","n":3,"i":417},{"t":"Bemani","n":3,"i":403},{"t":"女仆咖啡预备！","n":3,"i":402},{"t":"闲德淡藤协会","n":3,"u":"xddt"},{"t":"热血萝卜控","n":3,"i":353},{"t":"web 2.0","n":3,"u":"web"},{"t":"游戏基","n":3,"u":"game"},{"t":"美剧迷","n":3,"u":"ustv"},{"t":"午夜场","n":3,"i":275},{"t":"otaku宅化生存","n":3,"i":267},{"t":"萌三次元的打断腿","n":3,"u":"i2d"},{"t":"G.O.A","n":3,"i":207},{"t":"該小組已近被鸛貍猿 刪除","n":3,"i":206},{"t":"生化粉丝","n":3,"i":198},{"t":"全て远き理想郷","n":3,"i":197},{"t":"能登麻美子","n":3,"u":"notomamiko"},{"t":"KIRIKO/HIKO sound","n":3,"i":165},{"t":"窪之内英策","n":3,"i":151},{"t":"秋重学","n":3,"i":139},{"t":"其实我是高玩","n":3,"i":127},{"t":"ACG向Dance / Trance","n":3,"u":"acgdance"},{"t":"游戏部落","n":3,"i":72},{"t":"固有结界·萌系博爱","n":3,"i":64},{"t":"蓝色纱布阵营","n":3,"i":60},{"t":"口袋音乐","n":3,"i":59},{"t":"Pirate Party","n":3,"i":40},{"t":"好爸爸","n":3,"i":21},{"t":"落红组","n":3,"u":"virgin"},{"t":"战争雷霆","n":2,"i":4562},{"t":"哈猫快乐窝","n":2,"i":4558},{"t":"极地大乱斗","n":2,"u":"battleland"},{"t":"华语流行歌友会","n":2,"i":4546},{"t":"甘城なつき","n":2,"i":4540},{"t":"咖啡同好会","n":2,"u":"coffee"},{"t":"暗房","n":2,"i":4537},{"t":"中农sky动漫社番剧小组","n":2,"i":4536},{"t":"狗神煌","n":2,"i":4532},{"t":"Bebop","n":2,"i":4531},{"t":"Secret Party","n":2,"i":4524},{"t":"每天早上起床都是写不完的作业","n":2,"i":4516},{"t":"二次元语擦人聚集地","n":2,"u":"animie_rp"},{"t":"品霄番剧讨论","n":2,"i":4494},{"t":"哈比真可爱交流会","n":2,"i":4482},{"t":"电子既视感","n":2,"i":4481},{"t":"洛克王国手游","n":2,"i":4470},{"t":"gal兴趣小组","n":2,"u":"gal022"},{"t":"克洛斯贝尔支援科","n":2,"i":4464},{"t":"C某的心路历程","n":2,"i":4460},{"t":"瓶颈次元","n":2,"i":4457},{"t":"一起在线玩游戏","n":2,"u":"youxiwang"},{"t":"日区网飞NetflixJP资讯速递","n":2,"i":4447},{"t":"桑基鱼塘","n":2,"u":"mulberryfish"},{"t":"地球冒险","n":2,"i":4427},{"t":"Nagomi酱的小窝","n":2,"i":4412},{"t":"纯路人","n":2,"i":4399},{"t":"BGM交流","n":2,"i":4385},{"t":"Emacs","n":2,"i":4379},{"t":"新番","n":2,"i":4377},{"t":"已注销","n":2,"i":4370},{"t":"王者荣耀交流","n":2,"i":4364},{"t":"下班后炸鸡披萨麦茶会","n":2,"u":"ccgeass"},{"t":"The Silmarillion","n":2,"i":4346},{"t":"边框","n":2,"i":4342},{"t":"牛头人和鬼畜社团记录","n":2,"u":"ntr"},{"t":"bangumi哲学家","n":2,"i":4334},{"t":"Galgame分享","n":2,"i":4328},{"t":"ACG真宫作品探索协会","n":2,"i":4327},{"t":"我爱学习","n":2,"i":4319},{"t":".","n":2,"u":"bjyx"},{"t":"米兰球迷保护协会","n":2,"i":4315},{"t":"阿卡夏记录","n":2,"i":4311},{"t":"聊天","n":2,"u":"wend"},{"t":"ie","n":2,"i":4302},{"t":"PoC","n":2,"u":"poc_190818"},{"t":"东莞SOS团","n":2,"i":4293},{"t":"自我","n":2,"i":4285},{"t":"⭐️?","n":2,"u":"emoji"},{"t":".","n":2,"i":4269},{"t":"綜合","n":2,"u":"misc"},{"t":"其他","n":2,"u":"other"},{"t":"廣告","n":2,"u":"advertisements"},{"t":"根","n":2,"u":"root"},{"t":"发现","n":2,"u":"discover"},{"t":"食物","n":2,"u":"foods"},{"t":"异国恋","n":2,"i":4240},{"t":"白痴(白癡)","n":2,"i":4236},{"t":"The Star Guardians","n":2,"i":4227},{"t":"People With Believer","n":2,"u":"pwb"},{"t":"51","n":2,"i":4225},{"t":"自留","n":2,"u":"chiptune"},{"t":"日本战国历史","n":2,"i":4217},{"t":"狐狸的后门","n":2,"u":"hlandyess"},{"t":".0","n":2,"i":4202},{"t":"咆哮土拨鼠啊啊啊啊——","n":2,"i":4197},{"t":"不要让回忆变成空白","n":2,"i":4196},{"t":"时间线上的一点","n":2,"i":4189},{"t":"中二病也要谈恋爱","n":2,"u":"renai"},{"t":"300英雄","n":2,"i":4174},{"t":"堀江由衣","n":2,"i":4164},{"t":"エロゲー＆ギャルゲーの簡易データベース","n":2,"i":4162},{"t":"我们可能有个远大的梦想(仮)","n":2,"i":4151},{"t":"优化好友评价研讨会","n":2,"i":4143},{"t":"tucao","n":2,"i":4133},{"t":"Galileo Galilei","n":2,"i":4114},{"t":"megpoid_爱之遐想","n":2,"i":4109},{"t":"レオパレス204","n":2,"i":4108},{"t":"乃木板46","n":2,"i":4104},{"t":"波士顿废土建筑设计所","n":2,"i":4102},{"t":"猎奇向AVG","n":2,"i":4101},{"t":"纵横","n":2,"i":4095},{"t":"430の测试小组","n":2,"i":4087},{"t":"《换装衣橱》游戏体验","n":2,"u":"hzyc"},{"t":"江阴的同好一起来玩gal","n":2,"i":4085},{"t":"ツッコミ役","n":2,"i":4078},{"t":"天朝大圣任逍遥","n":2,"u":"arthurking"},{"t":"盗号者墓地","n":2,"u":"bgfhfg"},{"t":"ヒマワリ","n":2,"i":4048},{"t":"備份","n":2,"u":"unknown"},{"t":"樱子小姐的脚下埋着尸体","n":2,"i":4044},{"t":"阿幺の绘图工作室","n":2,"i":4039},{"t":"波士顿同好会","n":2,"i":4037},{"t":"让世界充满暗","n":2,"u":"black007"},{"t":"中村佑介","n":2,"i":4035},{"t":"EU/EEA/CH 欧洲联盟 欧洲经济区 瑞士联邦","n":2,"i":4034},{"t":"自成国度","n":2,"i":4027},{"t":"【音乐同志朋友募集】纸飞机の冒险","n":2,"i":4026},{"t":"TOHO CLOCK 东方同人微动画、音乐合作征集企划","n":2,"i":4024},{"t":"大艿艿爱好会","n":2,"i":4010},{"t":"*￣▽￣*)ブ","n":2,"i":4002},{"t":"求虐！吧唧","n":2,"u":"qiunue"},{"t":"字由文字办公室","n":2,"i":3829},{"t":"跪求CP 14.5一个摊位!!!寄售也可！求分！","n":2,"u":"woca_cppp"},{"t":"24H战争组","n":2,"i":3814},{"t":"滨州Cosplay同好会","n":2,"u":"bzcosplay"},{"t":"基三大本命","n":2,"u":"jisan"},{"t":"Earth OL","n":2,"i":3783},{"t":"布袋戏美强冷逆丧心病狂组","n":2,"i":3782},{"t":"贰分书院","n":2,"i":3779},{"t":"ACGMN博爱杂食党","n":2,"u":"animation"},{"t":"英雄伝说","n":2,"u":"eiyuudensetsu"},{"t":"动漫游戏宅集会所","n":2,"u":"zzs"},{"t":"宇宙彼星","n":2,"i":3759},{"t":"KGFicus","n":2,"u":"kgficus"},{"t":"イ菱","n":2,"i":3750},{"t":"来自风平浪静的明天","n":2,"i":3748},{"t":"數獨","n":2,"i":1637},{"t":"再也受不了","n":2,"u":"qqqqqsg"},{"t":"動物園zoo","n":2,"i":1620},{"t":"不能删的小组啦","n":2,"u":"dame"},{"t":"后宫公公大部队。Д。","n":2,"u":"dollard_"},{"t":"一念之差社团Yooo","n":2,"u":"yinianzhicha"},{"t":"Dribbble","n":2,"i":1596},{"t":"「L-Team」动漫CharacterPairing","n":2,"i":1592},{"t":"CHC独部","n":2,"i":1584},{"t":"Errors：非法力量","n":2,"i":1581},{"t":"一球入魂","n":2,"i":1565},{"t":"深夜报社组","n":2,"u":"midnightno"},{"t":"进击的巨人周边","n":2,"i":1550},{"t":"东三省同盟","n":2,"i":1543},{"t":"12L","n":2,"i":1539},{"t":"强权外交","n":2,"i":1538},{"t":"＿","n":2,"u":"jdaafg221"},{"t":"Muv-Luv","n":2,"i":1536},{"t":"舞蹈进化","n":2,"i":1534},{"t":"【朝颜组】招募淘宝管理已找到，感谢","n":2,"i":1532},{"t":"黄油联盟","n":2,"i":1531},{"t":"天朝内测服","n":2,"i":1502},{"t":"dx","n":2,"u":"ds"},{"t":"汐空字幕组","n":2,"i":1493},{"t":"就让我来把二姐拖入宅圈吧","n":2,"i":1476},{"t":"肉肉肉肉肉肉肉肉肉你媽","n":2,"i":1471},{"t":"zcghzgjzgh","n":2,"i":1463},{"t":"木加动漫社","n":2,"i":1460},{"t":"英语书插画组","n":2,"u":"englishpaint"},{"t":"諾森德企鵝組","n":2,"u":"nuosend"},{"t":"SEC组","n":2,"u":"sec3"},{"t":"关闭","n":2,"u":"cf"},{"t":"文学少女","n":2,"i":1430},{"t":"诸神的故乡","n":2,"i":1422},{"t":"非好感协会","n":2,"u":"fhgcos"},{"t":"肆歌动漫社团","n":2,"i":1405},{"t":"人妻控交流小组","n":2,"u":"mmmmm"},{"t":"丹麦语 (Dansk)","n":2,"i":1373},{"t":"软妹吧","n":2,"u":"rm"},{"t":"广西同好会","n":2,"u":"fj"},{"t":"知识","n":2,"i":1368},{"t":"广发动漫网","n":2,"u":"dsadasdas"},{"t":"洛克王国","n":2,"u":"iiihihi"},{"t":"战国BASARA","n":2,"i":1352},{"t":"\"▽\"倒三角","n":2,"i":1341},{"t":"森久保祥太郎","n":2,"i":1326},{"t":"DMS字幕组","n":2,"i":1325},{"t":"超游戏","n":2,"i":1321},{"t":"【supervision社团】","n":2,"i":1320},{"t":"叁_肆_境界线","n":2,"i":1313},{"t":"getbug","n":2,"u":"getbug"},{"t":"科学完全研究会","n":2,"i":1306},{"t":"A.I.","n":2,"i":1278},{"t":"-","n":2,"i":1276},{"t":"二號貨倉","n":2,"i":1270},{"t":"+S.N+","n":2,"u":"sn2205"},{"t":"aph20120815","n":2,"u":"aph20120815"},{"t":"印记城 City of Doors","n":2,"i":1255},{"t":"岁末笙歌oasis","n":2,"i":1249},{"t":"ひまわりの会","n":2,"i":1235},{"t":"MOJ`s studio","n":2,"u":"mojs_studio"},{"t":"日思录","n":2,"u":"selfrevolution"},{"t":"天际省人民政府","n":2,"i":1230},{"t":"神威GAKUPO♪","n":2,"u":"gakupo"},{"t":"ブクログ/Booklog","n":2,"i":1207},{"t":"記録用","n":2,"i":1199},{"t":"THE.I.C","n":2,"u":"ic"},{"t":"huke同好会","n":2,"i":1172},{"t":"创业者的家园","n":2,"i":1171},{"t":"西班牙语","n":2,"i":1169},{"t":"依然风采","n":2,"i":1166},{"t":"龙猫抱抱团","n":2,"i":1163},{"t":"超正规反抗分子","n":2,"i":1152},{"t":"KLAGE","n":2,"i":1120},{"t":"隐匿","n":2,"u":"lock"},{"t":"VAMPIRE血族","n":2,"i":1029},{"t":"优质大米","n":2,"u":"youzhidami"},{"t":"名言","n":2,"i":1024},{"t":"魔術協会","n":2,"u":"majutsukyoukai"},{"t":"骑士小组","n":2,"u":"kc518999"},{"t":"制服Ver.","n":2,"i":1007},{"t":"扑倒天然软妹","n":2,"i":1006},{"t":"つなこ","n":2,"i":1005},{"t":"月嶋ゆうこ","n":2,"i":1003},{"t":"笃见唯子","n":2,"i":1001},{"t":"未开拓HOME","n":2,"i":999},{"t":"幼馴染","n":2,"i":997},{"t":"隐宅大联盟","n":2,"u":"yingzhai"},{"t":"Archlich","n":2,"i":988},{"t":"翼之声中文配音社团","n":2,"i":986},{"t":"娱乐头条","n":2,"u":"yule2012"},{"t":"King.Of.Shou Works","n":2,"i":981},{"t":"细菌组","n":2,"u":"bacteria"},{"t":"武汉首届水都 冰蓝同人祭","n":2,"i":968},{"t":"Sandglass叙事组闲聊处（？）","n":2,"i":967},{"t":"彩虹堂","n":2,"u":"color_zone"},{"t":"水","n":2,"i":962},{"t":"水宅腐","n":2,"u":"szf"},{"t":"正统幻想书系同好会","n":2,"u":"fantasy"},{"t":"天工开墓","n":2,"i":944},{"t":"幻想乡驻沈阳办事处","n":2,"i":938},{"t":"妖孽王道","n":2,"i":935},{"t":"【废弃】","n":2,"i":925},{"t":"寻找遗失的愿望","n":2,"i":924},{"t":"暗夜凶光","n":2,"i":913},{"t":"木萌ACT-Animation Comices Team","n":2,"u":"act"},{"t":"天翼","n":2,"u":"gcg"},{"t":"独身公寓","n":2,"i":864},{"t":"寒露初雪组","n":2,"i":863},{"t":"那年夏天","n":2,"i":853},{"t":"Unity3D","n":2,"u":"unity3d"},{"t":"音乐控","n":2,"i":816},{"t":"益子正三郎NC颜饭同盟会","n":2,"i":812},{"t":"千茶组","n":2,"u":"qianchazu"},{"t":"午夜芥末党","n":2,"i":783},{"t":"patapon烧饼连锁店","n":2,"i":768},{"t":"动漫游戏REMIX","n":2,"i":759},{"t":"NPB","n":2,"i":757},{"t":"清澄高校麻将部","n":2,"i":756},{"t":"大牙狸","n":2,"u":"bidoof"},{"t":"0","n":2,"i":741},{"t":"盗墓笔祭","n":2,"i":737},{"t":"圆舞曲","n":2,"i":732},{"t":"疯狂怪医芙兰","n":2,"i":723},{"t":"塞法☆三千年的羁绊","n":2,"i":721},{"t":"神圣布莱蒂亚公国","n":2,"i":715},{"t":"咱们一起HAPPY。","n":2,"i":670},{"t":"網癮零番隊","n":2,"i":635},{"t":"御宅族-Otaku","n":2,"u":"otaku_acgnmdc"},{"t":"AKIBACD","n":2,"i":614},{"t":"装甲核心","n":2,"i":596},{"t":"BGM烟民俱乐部","n":2,"i":586},{"t":"尘世大陆冒险团，研究所救赎中","n":2,"i":517},{"t":"ASAの萌通信","n":2,"i":510},{"t":"z","n":2,"u":"z"},{"t":"Tynwald music","n":2,"i":492},{"t":"拌面据点","n":2,"i":447},{"t":"蛋疼症候群","n":2,"i":415},{"t":"伪鸟居","n":2,"i":405},{"t":"神曲奏界","n":2,"i":383},{"t":"漂亮同人堂","n":2,"u":"piaolf"},{"t":"午餐组","n":2,"i":313},{"t":"Monster Hunter","n":2,"u":"mh"},{"t":"装逼青年潜逃犯","n":2,"u":"b"},{"t":"高清控","n":2,"u":"bd"},{"t":"看电影","n":2,"u":"movie"},{"t":"Or2","n":2,"i":279},{"t":"OVA！","n":2,"u":"ova"},{"t":"动漫RSS","n":2,"i":271},{"t":"班固米观光团","n":2,"u":"guanguang"},{"t":"八卦播报","n":2,"i":269},{"t":"动漫字幕","n":2,"u":"sub"},{"t":"Pretty Cure","n":2,"i":253},{"t":"特拉斯电波站","n":2,"u":"npnc"},{"t":"要有爱，不要（哔——）","n":2,"i":214},{"t":"幽默笑话","n":2,"i":213},{"t":"所谓穿越","n":2,"u":"cy"},{"t":"ニコ厨","n":2,"i":188},{"t":"中原涼","n":2,"i":167},{"t":"美羽我可真是乱可爱一把的啊！","n":2,"i":87},{"t":"恶魔岛 大红莲团","n":2,"i":85},{"t":"任天狗","n":2,"i":76},{"t":"非限定性宅组","n":2,"i":65},{"t":"水~水~水组..54偶们吧！！...","n":2,"i":62},{"t":"低调地过来以给她毕生幸福为目标","n":2,"u":"lovesai"},{"t":"一般コミック","n":2,"i":51},{"t":"可逆性越境情报的跃迁","n":2,"i":19}]